<?xml version="1.0" encoding="UTF-8" standalone="yes" ?>
<!-- Generated with -sm /home/antor/didi-ext/pointnet/lidarnet-car-r3-x135-d45-seg-rings_12_28-sectors_32-epoch25-val_class_acc0.9992.hdf5 -lm /home/antor/didi-ext/pointnet/./lidarnet-car-r2-di-loc-rings_12_28-epoch34-val_loss0.0255.hdf5 -di -rfp -lpt 3 -b /home/antor/didi-ext/didi-data/release3/Data-points/testing/ford04.bag -->
<!DOCTYPE boost_serialization>
<boost_serialization signature="serialization::archive" version="9">
<tracklets class_id="0" tracking_level="0" version="0">
	<count>1</count>
	<item_version>1</item_version> 
	<item class_id="1" tracking_level="0" version="1">
		<objectType>Car</objectType>
		<h>1.484000</h>
		<w>1.823000</w>
		<l>4.358000</l>
		<first_frame>3</first_frame>
		<poses class_id="2" tracking_level="0" version="0">
			<count>163</count>
			<item_version>2</item_version>
			<!-- frame 3 -->
			<item class_id="3" tracking_level="0" version="2">
				<tx>25.162925</tx>
				<ty>-0.854729</ty>
				<tz>-0.925777</tz>
				<rx>0.000000</rx>
				<ry>0.000000</ry>
				<rz>-0.015391</rz>
				<state>0</state>
				<occlusion>-1</occlusion>
				<occlusion_kf>-1</occlusion_kf>
				<truncation>-1</truncation>
				<amt_occlusion>0.0</amt_occlusion>
				<amt_occlusion_kf>-1</amt_occlusion_kf>
				<amt_border_l>0.0</amt_border_l>
				<amt_border_r>0.0</amt_border_r>
				<amt_border_kf>-1</amt_border_kf>
			</item>
			<!-- frame 4 -->
			<item>
				<tx>25.162802</tx>
				<ty>-0.854530</ty>
				<tz>-0.925766</tz>
				<rx>0.000000</rx>
				<ry>0.000000</ry>
				<rz>-0.015391</rz>
				<state>0</state>
				<occlusion>-1</occlusion>
				<occlusion_kf>-1</occlusion_kf>
				<truncation>-1</truncation>
				<amt_occlusion>0.0</amt_occlusion>
				<amt_occlusion_kf>-1</amt_occlusion_kf>
				<amt_border_l>0.0</amt_border_l>
				<amt_border_r>0.0</amt_border_r>
				<amt_border_kf>-1</amt_border_kf>
			</item>
			<!-- frame 5 -->
			<item>
				<tx>25.105030</tx>
				<ty>-0.834927</ty>
				<tz>-0.927349</tz>
				<rx>0.000000</rx>
				<ry>0.000000</ry>
				<rz>-0.012677</rz>
				<state>0</state>
				<occlusion>-1</occlusion>
				<occlusion_kf>-1</occlusion_kf>
				<truncation>-1</truncation>
				<amt_occlusion>0.0</amt_occlusion>
				<amt_occlusion_kf>-1</amt_occlusion_kf>
				<amt_border_l>0.0</amt_border_l>
				<amt_border_r>0.0</amt_border_r>
				<amt_border_kf>-1</amt_border_kf>
			</item>
			<!-- frame 6 -->
			<item>
				<tx>25.102620</tx>
				<ty>-0.834051</ty>
				<tz>-0.927394</tz>
				<rx>0.000000</rx>
				<ry>0.000000</ry>
				<rz>-0.012677</rz>
				<state>0</state>
				<occlusion>-1</occlusion>
				<occlusion_kf>-1</occlusion_kf>
				<truncation>-1</truncation>
				<amt_occlusion>0.0</amt_occlusion>
				<amt_occlusion_kf>-1</amt_occlusion_kf>
				<amt_border_l>0.0</amt_border_l>
				<amt_border_r>0.0</amt_border_r>
				<amt_border_kf>-1</amt_border_kf>
			</item>
			<!-- frame 7 -->
			<item>
				<tx>25.037277</tx>
				<ty>-0.865938</ty>
				<tz>-0.968816</tz>
				<rx>0.000000</rx>
				<ry>0.000000</ry>
				<rz>-0.031212</rz>
				<state>0</state>
				<occlusion>-1</occlusion>
				<occlusion_kf>-1</occlusion_kf>
				<truncation>-1</truncation>
				<amt_occlusion>0.0</amt_occlusion>
				<amt_occlusion_kf>-1</amt_occlusion_kf>
				<amt_border_l>0.0</amt_border_l>
				<amt_border_r>0.0</amt_border_r>
				<amt_border_kf>-1</amt_border_kf>
			</item>
			<!-- frame 8 -->
			<item>
				<tx>25.029932</tx>
				<ty>-0.867021</ty>
				<tz>-0.971344</tz>
				<rx>0.000000</rx>
				<ry>0.000000</ry>
				<rz>-0.031212</rz>
				<state>0</state>
				<occlusion>-1</occlusion>
				<occlusion_kf>-1</occlusion_kf>
				<truncation>-1</truncation>
				<amt_occlusion>0.0</amt_occlusion>
				<amt_occlusion_kf>-1</amt_occlusion_kf>
				<amt_border_l>0.0</amt_border_l>
				<amt_border_r>0.0</amt_border_r>
				<amt_border_kf>-1</amt_border_kf>
			</item>
			<!-- frame 9 -->
			<item>
				<tx>25.022494</tx>
				<ty>-0.868117</ty>
				<tz>-0.973895</tz>
				<rx>0.000000</rx>
				<ry>0.000000</ry>
				<rz>-0.031212</rz>
				<state>0</state>
				<occlusion>-1</occlusion>
				<occlusion_kf>-1</occlusion_kf>
				<truncation>-1</truncation>
				<amt_occlusion>0.0</amt_occlusion>
				<amt_occlusion_kf>-1</amt_occlusion_kf>
				<amt_border_l>0.0</amt_border_l>
				<amt_border_r>0.0</amt_border_r>
				<amt_border_kf>-1</amt_border_kf>
			</item>
			<!-- frame 10 -->
			<item>
				<tx>24.903816</tx>
				<ty>-0.802732</ty>
				<tz>-1.006148</tz>
				<rx>0.000000</rx>
				<ry>0.000000</ry>
				<rz>-0.028320</rz>
				<state>0</state>
				<occlusion>-1</occlusion>
				<occlusion_kf>-1</occlusion_kf>
				<truncation>-1</truncation>
				<amt_occlusion>0.0</amt_occlusion>
				<amt_occlusion_kf>-1</amt_occlusion_kf>
				<amt_border_l>0.0</amt_border_l>
				<amt_border_r>0.0</amt_border_r>
				<amt_border_kf>-1</amt_border_kf>
			</item>
			<!-- frame 11 -->
			<item>
				<tx>24.886096</tx>
				<ty>-0.799706</ty>
				<tz>-1.010607</tz>
				<rx>0.000000</rx>
				<ry>0.000000</ry>
				<rz>-0.028320</rz>
				<state>0</state>
				<occlusion>-1</occlusion>
				<occlusion_kf>-1</occlusion_kf>
				<truncation>-1</truncation>
				<amt_occlusion>0.0</amt_occlusion>
				<amt_occlusion_kf>-1</amt_occlusion_kf>
				<amt_border_l>0.0</amt_border_l>
				<amt_border_r>0.0</amt_border_r>
				<amt_border_kf>-1</amt_border_kf>
			</item>
			<!-- frame 12 -->
			<item>
				<tx>24.743486</tx>
				<ty>-0.785079</ty>
				<tz>-1.021085</tz>
				<rx>0.000000</rx>
				<ry>0.000000</ry>
				<rz>-0.016606</rz>
				<state>0</state>
				<occlusion>-1</occlusion>
				<occlusion_kf>-1</occlusion_kf>
				<truncation>-1</truncation>
				<amt_occlusion>0.0</amt_occlusion>
				<amt_occlusion_kf>-1</amt_occlusion_kf>
				<amt_border_l>0.0</amt_border_l>
				<amt_border_r>0.0</amt_border_r>
				<amt_border_kf>-1</amt_border_kf>
			</item>
			<!-- frame 13 -->
			<item>
				<tx>24.711233</tx>
				<ty>-0.781196</ty>
				<tz>-1.026028</tz>
				<rx>0.000000</rx>
				<ry>0.000000</ry>
				<rz>-0.016606</rz>
				<state>0</state>
				<occlusion>-1</occlusion>
				<occlusion_kf>-1</occlusion_kf>
				<truncation>-1</truncation>
				<amt_occlusion>0.0</amt_occlusion>
				<amt_occlusion_kf>-1</amt_occlusion_kf>
				<amt_border_l>0.0</amt_border_l>
				<amt_border_r>0.0</amt_border_r>
				<amt_border_kf>-1</amt_border_kf>
			</item>
			<!-- frame 14 -->
			<item>
				<tx>24.678183</tx>
				<ty>-0.777267</ty>
				<tz>-1.031020</tz>
				<rx>0.000000</rx>
				<ry>0.000000</ry>
				<rz>-0.016606</rz>
				<state>0</state>
				<occlusion>-1</occlusion>
				<occlusion_kf>-1</occlusion_kf>
				<truncation>-1</truncation>
				<amt_occlusion>0.0</amt_occlusion>
				<amt_occlusion_kf>-1</amt_occlusion_kf>
				<amt_border_l>0.0</amt_border_l>
				<amt_border_r>0.0</amt_border_r>
				<amt_border_kf>-1</amt_border_kf>
			</item>
			<!-- frame 15 -->
			<item>
				<tx>24.528844</tx>
				<ty>-0.768659</ty>
				<tz>-1.026559</tz>
				<rx>0.000000</rx>
				<ry>0.000000</ry>
				<rz>-0.017872</rz>
				<state>0</state>
				<occlusion>-1</occlusion>
				<occlusion_kf>-1</occlusion_kf>
				<truncation>-1</truncation>
				<amt_occlusion>0.0</amt_occlusion>
				<amt_occlusion_kf>-1</amt_occlusion_kf>
				<amt_border_l>0.0</amt_border_l>
				<amt_border_r>0.0</amt_border_r>
				<amt_border_kf>-1</amt_border_kf>
			</item>
			<!-- frame 16 -->
			<item>
				<tx>24.481456</tx>
				<ty>-0.764365</ty>
				<tz>-1.031034</tz>
				<rx>0.000000</rx>
				<ry>0.000000</ry>
				<rz>-0.017872</rz>
				<state>0</state>
				<occlusion>-1</occlusion>
				<occlusion_kf>-1</occlusion_kf>
				<truncation>-1</truncation>
				<amt_occlusion>0.0</amt_occlusion>
				<amt_occlusion_kf>-1</amt_occlusion_kf>
				<amt_border_l>0.0</amt_border_l>
				<amt_border_r>0.0</amt_border_r>
				<amt_border_kf>-1</amt_border_kf>
			</item>
			<!-- frame 17 -->
			<item>
				<tx>24.236660</tx>
				<ty>-0.646067</ty>
				<tz>-1.113066</tz>
				<rx>0.000000</rx>
				<ry>0.000000</ry>
				<rz>0.003228</rz>
				<state>0</state>
				<occlusion>-1</occlusion>
				<occlusion_kf>-1</occlusion_kf>
				<truncation>-1</truncation>
				<amt_occlusion>0.0</amt_occlusion>
				<amt_occlusion_kf>-1</amt_occlusion_kf>
				<amt_border_l>0.0</amt_border_l>
				<amt_border_r>0.0</amt_border_r>
				<amt_border_kf>-1</amt_border_kf>
			</item>
			<!-- frame 18 -->
			<item>
				<tx>24.160980</tx>
				<ty>-0.633999</ty>
				<tz>-1.122841</tz>
				<rx>0.000000</rx>
				<ry>0.000000</ry>
				<rz>0.003228</rz>
				<state>0</state>
				<occlusion>-1</occlusion>
				<occlusion_kf>-1</occlusion_kf>
				<truncation>-1</truncation>
				<amt_occlusion>0.0</amt_occlusion>
				<amt_occlusion_kf>-1</amt_occlusion_kf>
				<amt_border_l>0.0</amt_border_l>
				<amt_border_r>0.0</amt_border_r>
				<amt_border_kf>-1</amt_border_kf>
			</item>
			<!-- frame 19 -->
			<item>
				<tx>24.025669</tx>
				<ty>-0.512761</ty>
				<tz>-1.075971</tz>
				<rx>0.000000</rx>
				<ry>0.000000</ry>
				<rz>0.000011</rz>
				<state>0</state>
				<occlusion>-1</occlusion>
				<occlusion_kf>-1</occlusion_kf>
				<truncation>-1</truncation>
				<amt_occlusion>0.0</amt_occlusion>
				<amt_occlusion_kf>-1</amt_occlusion_kf>
				<amt_border_l>0.0</amt_border_l>
				<amt_border_r>0.0</amt_border_r>
				<amt_border_kf>-1</amt_border_kf>
			</item>
			<!-- frame 20 -->
			<item>
				<tx>23.936922</tx>
				<ty>-0.492751</ty>
				<tz>-1.082037</tz>
				<rx>0.000000</rx>
				<ry>0.000000</ry>
				<rz>0.000011</rz>
				<state>0</state>
				<occlusion>-1</occlusion>
				<occlusion_kf>-1</occlusion_kf>
				<truncation>-1</truncation>
				<amt_occlusion>0.0</amt_occlusion>
				<amt_occlusion_kf>-1</amt_occlusion_kf>
				<amt_border_l>0.0</amt_border_l>
				<amt_border_r>0.0</amt_border_r>
				<amt_border_kf>-1</amt_border_kf>
			</item>
			<!-- frame 21 -->
			<item>
				<tx>23.844935</tx>
				<ty>-0.472325</ty>
				<tz>-1.088173</tz>
				<rx>0.000000</rx>
				<ry>0.000000</ry>
				<rz>0.000011</rz>
				<state>0</state>
				<occlusion>-1</occlusion>
				<occlusion_kf>-1</occlusion_kf>
				<truncation>-1</truncation>
				<amt_occlusion>0.0</amt_occlusion>
				<amt_occlusion_kf>-1</amt_occlusion_kf>
				<amt_border_l>0.0</amt_border_l>
				<amt_border_r>0.0</amt_border_r>
				<amt_border_kf>-1</amt_border_kf>
			</item>
			<!-- frame 22 -->
			<item>
				<tx>23.656072</tx>
				<ty>-0.465875</ty>
				<tz>-1.089214</tz>
				<rx>0.000000</rx>
				<ry>0.000000</ry>
				<rz>0.004130</rz>
				<state>0</state>
				<occlusion>-1</occlusion>
				<occlusion_kf>-1</occlusion_kf>
				<truncation>-1</truncation>
				<amt_occlusion>0.0</amt_occlusion>
				<amt_occlusion_kf>-1</amt_occlusion_kf>
				<amt_border_l>0.0</amt_border_l>
				<amt_border_r>0.0</amt_border_r>
				<amt_border_kf>-1</amt_border_kf>
			</item>
			<!-- frame 23 -->
			<item>
				<tx>23.545482</tx>
				<ty>-0.445640</ty>
				<tz>-1.095128</tz>
				<rx>0.000000</rx>
				<ry>0.000000</ry>
				<rz>0.004130</rz>
				<state>0</state>
				<occlusion>-1</occlusion>
				<occlusion_kf>-1</occlusion_kf>
				<truncation>-1</truncation>
				<amt_occlusion>0.0</amt_occlusion>
				<amt_occlusion_kf>-1</amt_occlusion_kf>
				<amt_border_l>0.0</amt_border_l>
				<amt_border_r>0.0</amt_border_r>
				<amt_border_kf>-1</amt_border_kf>
			</item>
			<!-- frame 24 -->
			<item>
				<tx>23.364985</tx>
				<ty>-0.535763</ty>
				<tz>-1.018769</tz>
				<rx>0.000000</rx>
				<ry>0.000000</ry>
				<rz>-0.023042</rz>
				<state>0</state>
				<occlusion>-1</occlusion>
				<occlusion_kf>-1</occlusion_kf>
				<truncation>-1</truncation>
				<amt_occlusion>0.0</amt_occlusion>
				<amt_occlusion_kf>-1</amt_occlusion_kf>
				<amt_border_l>0.0</amt_border_l>
				<amt_border_r>0.0</amt_border_r>
				<amt_border_kf>-1</amt_border_kf>
			</item>
			<!-- frame 25 -->
			<item>
				<tx>23.237036</tx>
				<ty>-0.522315</ty>
				<tz>-1.019216</tz>
				<rx>0.000000</rx>
				<ry>0.000000</ry>
				<rz>-0.023042</rz>
				<state>0</state>
				<occlusion>-1</occlusion>
				<occlusion_kf>-1</occlusion_kf>
				<truncation>-1</truncation>
				<amt_occlusion>0.0</amt_occlusion>
				<amt_occlusion_kf>-1</amt_occlusion_kf>
				<amt_border_l>0.0</amt_border_l>
				<amt_border_r>0.0</amt_border_r>
				<amt_border_kf>-1</amt_border_kf>
			</item>
			<!-- frame 26 -->
			<item>
				<tx>23.105520</tx>
				<ty>-0.508779</ty>
				<tz>-1.019570</tz>
				<rx>0.000000</rx>
				<ry>0.000000</ry>
				<rz>-0.023042</rz>
				<state>0</state>
				<occlusion>-1</occlusion>
				<occlusion_kf>-1</occlusion_kf>
				<truncation>-1</truncation>
				<amt_occlusion>0.0</amt_occlusion>
				<amt_occlusion_kf>-1</amt_occlusion_kf>
				<amt_border_l>0.0</amt_border_l>
				<amt_border_r>0.0</amt_border_r>
				<amt_border_kf>-1</amt_border_kf>
			</item>
			<!-- frame 27 -->
			<item>
				<tx>22.938125</tx>
				<ty>-0.537710</ty>
				<tz>-0.977979</tz>
				<rx>0.000000</rx>
				<ry>0.000000</ry>
				<rz>-0.016828</rz>
				<state>0</state>
				<occlusion>-1</occlusion>
				<occlusion_kf>-1</occlusion_kf>
				<truncation>-1</truncation>
				<amt_occlusion>0.0</amt_occlusion>
				<amt_occlusion_kf>-1</amt_occlusion_kf>
				<amt_border_l>0.0</amt_border_l>
				<amt_border_r>0.0</amt_border_r>
				<amt_border_kf>-1</amt_border_kf>
			</item>
			<!-- frame 28 -->
			<item>
				<tx>22.793240</tx>
				<ty>-0.526465</ty>
				<tz>-0.975542</tz>
				<rx>0.000000</rx>
				<ry>0.000000</ry>
				<rz>-0.016828</rz>
				<state>0</state>
				<occlusion>-1</occlusion>
				<occlusion_kf>-1</occlusion_kf>
				<truncation>-1</truncation>
				<amt_occlusion>0.0</amt_occlusion>
				<amt_occlusion_kf>-1</amt_occlusion_kf>
				<amt_border_l>0.0</amt_border_l>
				<amt_border_r>0.0</amt_border_r>
				<amt_border_kf>-1</amt_border_kf>
			</item>
			<!-- frame 29 -->
			<item>
				<tx>22.637086</tx>
				<ty>-0.521656</ty>
				<tz>-0.999170</tz>
				<rx>0.000000</rx>
				<ry>0.000000</ry>
				<rz>-0.014420</rz>
				<state>0</state>
				<occlusion>-1</occlusion>
				<occlusion_kf>-1</occlusion_kf>
				<truncation>-1</truncation>
				<amt_occlusion>0.0</amt_occlusion>
				<amt_occlusion_kf>-1</amt_occlusion_kf>
				<amt_border_l>0.0</amt_border_l>
				<amt_border_r>0.0</amt_border_r>
				<amt_border_kf>-1</amt_border_kf>
			</item>
			<!-- frame 30 -->
			<item>
				<tx>22.482329</tx>
				<ty>-0.510683</ty>
				<tz>-0.998194</tz>
				<rx>0.000000</rx>
				<ry>0.000000</ry>
				<rz>-0.014420</rz>
				<state>0</state>
				<occlusion>-1</occlusion>
				<occlusion_kf>-1</occlusion_kf>
				<truncation>-1</truncation>
				<amt_occlusion>0.0</amt_occlusion>
				<amt_occlusion_kf>-1</amt_occlusion_kf>
				<amt_border_l>0.0</amt_border_l>
				<amt_border_r>0.0</amt_border_r>
				<amt_border_kf>-1</amt_border_kf>
			</item>
			<!-- frame 31 -->
			<item>
				<tx>22.317379</tx>
				<ty>-0.474609</ty>
				<tz>-1.011354</tz>
				<rx>0.000000</rx>
				<ry>0.000000</ry>
				<rz>-0.015710</rz>
				<state>0</state>
				<occlusion>-1</occlusion>
				<occlusion_kf>-1</occlusion_kf>
				<truncation>-1</truncation>
				<amt_occlusion>0.0</amt_occlusion>
				<amt_occlusion_kf>-1</amt_occlusion_kf>
				<amt_border_l>0.0</amt_border_l>
				<amt_border_r>0.0</amt_border_r>
				<amt_border_kf>-1</amt_border_kf>
			</item>
			<!-- frame 32 -->
			<item>
				<tx>22.153015</tx>
				<ty>-0.461737</ty>
				<tz>-1.011167</tz>
				<rx>0.000000</rx>
				<ry>0.000000</ry>
				<rz>-0.015710</rz>
				<state>0</state>
				<occlusion>-1</occlusion>
				<occlusion_kf>-1</occlusion_kf>
				<truncation>-1</truncation>
				<amt_occlusion>0.0</amt_occlusion>
				<amt_occlusion_kf>-1</amt_occlusion_kf>
				<amt_border_l>0.0</amt_border_l>
				<amt_border_r>0.0</amt_border_r>
				<amt_border_kf>-1</amt_border_kf>
			</item>
			<!-- frame 33 -->
			<item>
				<tx>21.983237</tx>
				<ty>-0.448676</ty>
				<tz>-1.010894</tz>
				<rx>0.000000</rx>
				<ry>0.000000</ry>
				<rz>-0.015710</rz>
				<state>0</state>
				<occlusion>-1</occlusion>
				<occlusion_kf>-1</occlusion_kf>
				<truncation>-1</truncation>
				<amt_occlusion>0.0</amt_occlusion>
				<amt_occlusion_kf>-1</amt_occlusion_kf>
				<amt_border_l>0.0</amt_border_l>
				<amt_border_r>0.0</amt_border_r>
				<amt_border_kf>-1</amt_border_kf>
			</item>
			<!-- frame 34 -->
			<item>
				<tx>21.804866</tx>
				<ty>-0.403908</ty>
				<tz>-0.999048</tz>
				<rx>0.000000</rx>
				<ry>0.000000</ry>
				<rz>0.005742</rz>
				<state>0</state>
				<occlusion>-1</occlusion>
				<occlusion_kf>-1</occlusion_kf>
				<truncation>-1</truncation>
				<amt_occlusion>0.0</amt_occlusion>
				<amt_occlusion_kf>-1</amt_occlusion_kf>
				<amt_border_l>0.0</amt_border_l>
				<amt_border_r>0.0</amt_border_r>
				<amt_border_kf>-1</amt_border_kf>
			</item>
			<!-- frame 35 -->
			<item>
				<tx>21.625626</tx>
				<ty>-0.388596</ty>
				<tz>-0.997868</tz>
				<rx>0.000000</rx>
				<ry>0.000000</ry>
				<rz>0.005742</rz>
				<state>0</state>
				<occlusion>-1</occlusion>
				<occlusion_kf>-1</occlusion_kf>
				<truncation>-1</truncation>
				<amt_occlusion>0.0</amt_occlusion>
				<amt_occlusion_kf>-1</amt_occlusion_kf>
				<amt_border_l>0.0</amt_border_l>
				<amt_border_r>0.0</amt_border_r>
				<amt_border_kf>-1</amt_border_kf>
			</item>
			<!-- frame 36 -->
			<item>
				<tx>21.482835</tx>
				<ty>-0.372744</ty>
				<tz>-0.971549</tz>
				<rx>0.000000</rx>
				<ry>0.000000</ry>
				<rz>-0.016584</rz>
				<state>0</state>
				<occlusion>-1</occlusion>
				<occlusion_kf>-1</occlusion_kf>
				<truncation>-1</truncation>
				<amt_occlusion>0.0</amt_occlusion>
				<amt_occlusion_kf>-1</amt_occlusion_kf>
				<amt_border_l>0.0</amt_border_l>
				<amt_border_r>0.0</amt_border_r>
				<amt_border_kf>-1</amt_border_kf>
			</item>
			<!-- frame 37 -->
			<item>
				<tx>21.301474</tx>
				<ty>-0.357123</ty>
				<tz>-0.968449</tz>
				<rx>0.000000</rx>
				<ry>0.000000</ry>
				<rz>-0.016584</rz>
				<state>0</state>
				<occlusion>-1</occlusion>
				<occlusion_kf>-1</occlusion_kf>
				<truncation>-1</truncation>
				<amt_occlusion>0.0</amt_occlusion>
				<amt_occlusion_kf>-1</amt_occlusion_kf>
				<amt_border_l>0.0</amt_border_l>
				<amt_border_r>0.0</amt_border_r>
				<amt_border_kf>-1</amt_border_kf>
			</item>
			<!-- frame 38 -->
			<item>
				<tx>21.114999</tx>
				<ty>-0.341250</ty>
				<tz>-0.965184</tz>
				<rx>0.000000</rx>
				<ry>0.000000</ry>
				<rz>-0.016584</rz>
				<state>0</state>
				<occlusion>-1</occlusion>
				<occlusion_kf>-1</occlusion_kf>
				<truncation>-1</truncation>
				<amt_occlusion>0.0</amt_occlusion>
				<amt_occlusion_kf>-1</amt_occlusion_kf>
				<amt_border_l>0.0</amt_border_l>
				<amt_border_r>0.0</amt_border_r>
				<amt_border_kf>-1</amt_border_kf>
			</item>
			<!-- frame 39 -->
			<item>
				<tx>20.892821</tx>
				<ty>-0.349385</ty>
				<tz>-0.941294</tz>
				<rx>0.000000</rx>
				<ry>0.000000</ry>
				<rz>-0.017759</rz>
				<state>0</state>
				<occlusion>-1</occlusion>
				<occlusion_kf>-1</occlusion_kf>
				<truncation>-1</truncation>
				<amt_occlusion>0.0</amt_occlusion>
				<amt_occlusion_kf>-1</amt_occlusion_kf>
				<amt_border_l>0.0</amt_border_l>
				<amt_border_r>0.0</amt_border_r>
				<amt_border_kf>-1</amt_border_kf>
			</item>
			<!-- frame 40 -->
			<item>
				<tx>20.706154</tx>
				<ty>-0.335578</ty>
				<tz>-0.936723</tz>
				<rx>0.000000</rx>
				<ry>0.000000</ry>
				<rz>-0.017759</rz>
				<state>0</state>
				<occlusion>-1</occlusion>
				<occlusion_kf>-1</occlusion_kf>
				<truncation>-1</truncation>
				<amt_occlusion>0.0</amt_occlusion>
				<amt_occlusion_kf>-1</amt_occlusion_kf>
				<amt_border_l>0.0</amt_border_l>
				<amt_border_r>0.0</amt_border_r>
				<amt_border_kf>-1</amt_border_kf>
			</item>
			<!-- frame 41 -->
			<item>
				<tx>20.514595</tx>
				<ty>-0.296655</ty>
				<tz>-0.922081</tz>
				<rx>0.000000</rx>
				<ry>0.000000</ry>
				<rz>-0.018780</rz>
				<state>0</state>
				<occlusion>-1</occlusion>
				<occlusion_kf>-1</occlusion_kf>
				<truncation>-1</truncation>
				<amt_occlusion>0.0</amt_occlusion>
				<amt_occlusion_kf>-1</amt_occlusion_kf>
				<amt_border_l>0.0</amt_border_l>
				<amt_border_r>0.0</amt_border_r>
				<amt_border_kf>-1</amt_border_kf>
			</item>
			<!-- frame 42 -->
			<item>
				<tx>20.310121</tx>
				<ty>-0.280146</ty>
				<tz>-0.916237</tz>
				<rx>0.000000</rx>
				<ry>0.000000</ry>
				<rz>-0.018780</rz>
				<state>0</state>
				<occlusion>-1</occlusion>
				<occlusion_kf>-1</occlusion_kf>
				<truncation>-1</truncation>
				<amt_occlusion>0.0</amt_occlusion>
				<amt_occlusion_kf>-1</amt_occlusion_kf>
				<amt_border_l>0.0</amt_border_l>
				<amt_border_r>0.0</amt_border_r>
				<amt_border_kf>-1</amt_border_kf>
			</item>
			<!-- frame 43 -->
			<item>
				<tx>20.093267</tx>
				<ty>-0.263653</ty>
				<tz>-0.897530</tz>
				<rx>0.000000</rx>
				<ry>0.000000</ry>
				<rz>-0.020547</rz>
				<state>0</state>
				<occlusion>-1</occlusion>
				<occlusion_kf>-1</occlusion_kf>
				<truncation>-1</truncation>
				<amt_occlusion>0.0</amt_occlusion>
				<amt_occlusion_kf>-1</amt_occlusion_kf>
				<amt_border_l>0.0</amt_border_l>
				<amt_border_r>0.0</amt_border_r>
				<amt_border_kf>-1</amt_border_kf>
			</item>
			<!-- frame 44 -->
			<item>
				<tx>19.865961</tx>
				<ty>-0.245786</ty>
				<tz>-0.889958</tz>
				<rx>0.000000</rx>
				<ry>0.000000</ry>
				<rz>-0.020547</rz>
				<state>0</state>
				<occlusion>-1</occlusion>
				<occlusion_kf>-1</occlusion_kf>
				<truncation>-1</truncation>
				<amt_occlusion>0.0</amt_occlusion>
				<amt_occlusion_kf>-1</amt_occlusion_kf>
				<amt_border_l>0.0</amt_border_l>
				<amt_border_r>0.0</amt_border_r>
				<amt_border_kf>-1</amt_border_kf>
			</item>
			<!-- frame 45 -->
			<item>
				<tx>19.659140</tx>
				<ty>-0.229687</ty>
				<tz>-0.882997</tz>
				<rx>0.000000</rx>
				<ry>0.000000</ry>
				<rz>-0.020547</rz>
				<state>0</state>
				<occlusion>-1</occlusion>
				<occlusion_kf>-1</occlusion_kf>
				<truncation>-1</truncation>
				<amt_occlusion>0.0</amt_occlusion>
				<amt_occlusion_kf>-1</amt_occlusion_kf>
				<amt_border_l>0.0</amt_border_l>
				<amt_border_r>0.0</amt_border_r>
				<amt_border_kf>-1</amt_border_kf>
			</item>
			<!-- frame 46 -->
			<item>
				<tx>19.433848</tx>
				<ty>-0.248596</ty>
				<tz>-0.884946</tz>
				<rx>0.000000</rx>
				<ry>0.000000</ry>
				<rz>-0.029344</rz>
				<state>0</state>
				<occlusion>-1</occlusion>
				<occlusion_kf>-1</occlusion_kf>
				<truncation>-1</truncation>
				<amt_occlusion>0.0</amt_occlusion>
				<amt_occlusion_kf>-1</amt_occlusion_kf>
				<amt_border_l>0.0</amt_border_l>
				<amt_border_r>0.0</amt_border_r>
				<amt_border_kf>-1</amt_border_kf>
			</item>
			<!-- frame 47 -->
			<item>
				<tx>19.206522</tx>
				<ty>-0.233542</ty>
				<tz>-0.877767</tz>
				<rx>0.000000</rx>
				<ry>0.000000</ry>
				<rz>-0.029344</rz>
				<state>0</state>
				<occlusion>-1</occlusion>
				<occlusion_kf>-1</occlusion_kf>
				<truncation>-1</truncation>
				<amt_occlusion>0.0</amt_occlusion>
				<amt_occlusion_kf>-1</amt_occlusion_kf>
				<amt_border_l>0.0</amt_border_l>
				<amt_border_r>0.0</amt_border_r>
				<amt_border_kf>-1</amt_border_kf>
			</item>
			<!-- frame 48 -->
			<item>
				<tx>19.037443</tx>
				<ty>-0.237619</ty>
				<tz>-0.899601</tz>
				<rx>0.000000</rx>
				<ry>0.000000</ry>
				<rz>-0.010689</rz>
				<state>0</state>
				<occlusion>-1</occlusion>
				<occlusion_kf>-1</occlusion_kf>
				<truncation>-1</truncation>
				<amt_occlusion>0.0</amt_occlusion>
				<amt_occlusion_kf>-1</amt_occlusion_kf>
				<amt_border_l>0.0</amt_border_l>
				<amt_border_r>0.0</amt_border_r>
				<amt_border_kf>-1</amt_border_kf>
			</item>
			<!-- frame 49 -->
			<item>
				<tx>18.797009</tx>
				<ty>-0.222769</ty>
				<tz>-0.893644</tz>
				<rx>0.000000</rx>
				<ry>0.000000</ry>
				<rz>-0.010689</rz>
				<state>0</state>
				<occlusion>-1</occlusion>
				<occlusion_kf>-1</occlusion_kf>
				<truncation>-1</truncation>
				<amt_occlusion>0.0</amt_occlusion>
				<amt_occlusion_kf>-1</amt_occlusion_kf>
				<amt_border_l>0.0</amt_border_l>
				<amt_border_r>0.0</amt_border_r>
				<amt_border_kf>-1</amt_border_kf>
			</item>
			<!-- frame 50 -->
			<item>
				<tx>18.579033</tx>
				<ty>-0.209446</ty>
				<tz>-0.888185</tz>
				<rx>0.000000</rx>
				<ry>0.000000</ry>
				<rz>-0.010689</rz>
				<state>0</state>
				<occlusion>-1</occlusion>
				<occlusion_kf>-1</occlusion_kf>
				<truncation>-1</truncation>
				<amt_occlusion>0.0</amt_occlusion>
				<amt_occlusion_kf>-1</amt_occlusion_kf>
				<amt_border_l>0.0</amt_border_l>
				<amt_border_r>0.0</amt_border_r>
				<amt_border_kf>-1</amt_border_kf>
			</item>
			<!-- frame 51 -->
			<item>
				<tx>18.357853</tx>
				<ty>-0.195336</ty>
				<tz>-0.877503</tz>
				<rx>0.000000</rx>
				<ry>0.000000</ry>
				<rz>0.012545</rz>
				<state>0</state>
				<occlusion>-1</occlusion>
				<occlusion_kf>-1</occlusion_kf>
				<truncation>-1</truncation>
				<amt_occlusion>0.0</amt_occlusion>
				<amt_occlusion_kf>-1</amt_occlusion_kf>
				<amt_border_l>0.0</amt_border_l>
				<amt_border_r>0.0</amt_border_r>
				<amt_border_kf>-1</amt_border_kf>
			</item>
			<!-- frame 52 -->
			<item>
				<tx>18.120801</tx>
				<ty>-0.181028</ty>
				<tz>-0.871105</tz>
				<rx>0.000000</rx>
				<ry>0.000000</ry>
				<rz>0.012545</rz>
				<state>0</state>
				<occlusion>-1</occlusion>
				<occlusion_kf>-1</occlusion_kf>
				<truncation>-1</truncation>
				<amt_occlusion>0.0</amt_occlusion>
				<amt_occlusion_kf>-1</amt_occlusion_kf>
				<amt_border_l>0.0</amt_border_l>
				<amt_border_r>0.0</amt_border_r>
				<amt_border_kf>-1</amt_border_kf>
			</item>
			<!-- frame 53 -->
			<item>
				<tx>17.827333</tx>
				<ty>-0.216331</ty>
				<tz>-0.851229</tz>
				<rx>0.000000</rx>
				<ry>0.000000</ry>
				<rz>0.050242</rz>
				<state>0</state>
				<occlusion>-1</occlusion>
				<occlusion_kf>-1</occlusion_kf>
				<truncation>-1</truncation>
				<amt_occlusion>0.0</amt_occlusion>
				<amt_occlusion_kf>-1</amt_occlusion_kf>
				<amt_border_l>0.0</amt_border_l>
				<amt_border_r>0.0</amt_border_r>
				<amt_border_kf>-1</amt_border_kf>
			</item>
			<!-- frame 54 -->
			<item>
				<tx>17.560271</tx>
				<ty>-0.204523</ty>
				<tz>-0.843176</tz>
				<rx>0.000000</rx>
				<ry>0.000000</ry>
				<rz>0.050242</rz>
				<state>0</state>
				<occlusion>-1</occlusion>
				<occlusion_kf>-1</occlusion_kf>
				<truncation>-1</truncation>
				<amt_occlusion>0.0</amt_occlusion>
				<amt_occlusion_kf>-1</amt_occlusion_kf>
				<amt_border_l>0.0</amt_border_l>
				<amt_border_r>0.0</amt_border_r>
				<amt_border_kf>-1</amt_border_kf>
			</item>
			<!-- frame 55 -->
			<item>
				<tx>17.449139</tx>
				<ty>-0.214830</ty>
				<tz>-0.829896</tz>
				<rx>0.000000</rx>
				<ry>0.000000</ry>
				<rz>0.003863</rz>
				<state>0</state>
				<occlusion>-1</occlusion>
				<occlusion_kf>-1</occlusion_kf>
				<truncation>-1</truncation>
				<amt_occlusion>0.0</amt_occlusion>
				<amt_occlusion_kf>-1</amt_occlusion_kf>
				<amt_border_l>0.0</amt_border_l>
				<amt_border_r>0.0</amt_border_r>
				<amt_border_kf>-1</amt_border_kf>
			</item>
			<!-- frame 56 -->
			<item>
				<tx>17.208614</tx>
				<ty>-0.205070</ty>
				<tz>-0.821491</tz>
				<rx>0.000000</rx>
				<ry>0.000000</ry>
				<rz>0.003863</rz>
				<state>0</state>
				<occlusion>-1</occlusion>
				<occlusion_kf>-1</occlusion_kf>
				<truncation>-1</truncation>
				<amt_occlusion>0.0</amt_occlusion>
				<amt_occlusion_kf>-1</amt_occlusion_kf>
				<amt_border_l>0.0</amt_border_l>
				<amt_border_r>0.0</amt_border_r>
				<amt_border_kf>-1</amt_border_kf>
			</item>
			<!-- frame 57 -->
			<item>
				<tx>16.965781</tx>
				<ty>-0.195364</ty>
				<tz>-0.812916</tz>
				<rx>0.000000</rx>
				<ry>0.000000</ry>
				<rz>0.003863</rz>
				<state>0</state>
				<occlusion>-1</occlusion>
				<occlusion_kf>-1</occlusion_kf>
				<truncation>-1</truncation>
				<amt_occlusion>0.0</amt_occlusion>
				<amt_occlusion_kf>-1</amt_occlusion_kf>
				<amt_border_l>0.0</amt_border_l>
				<amt_border_r>0.0</amt_border_r>
				<amt_border_kf>-1</amt_border_kf>
			</item>
			<!-- frame 58 -->
			<item>
				<tx>16.842497</tx>
				<ty>-0.253782</ty>
				<tz>-0.811017</tz>
				<rx>0.000000</rx>
				<ry>0.000000</ry>
				<rz>-0.013131</rz>
				<state>0</state>
				<occlusion>-1</occlusion>
				<occlusion_kf>-1</occlusion_kf>
				<truncation>-1</truncation>
				<amt_occlusion>0.0</amt_occlusion>
				<amt_occlusion_kf>-1</amt_occlusion_kf>
				<amt_border_l>0.0</amt_border_l>
				<amt_border_r>0.0</amt_border_r>
				<amt_border_kf>-1</amt_border_kf>
			</item>
			<!-- frame 59 -->
			<item>
				<tx>16.597087</tx>
				<ty>-0.248019</ty>
				<tz>-0.801953</tz>
				<rx>0.000000</rx>
				<ry>0.000000</ry>
				<rz>-0.013131</rz>
				<state>0</state>
				<occlusion>-1</occlusion>
				<occlusion_kf>-1</occlusion_kf>
				<truncation>-1</truncation>
				<amt_occlusion>0.0</amt_occlusion>
				<amt_occlusion_kf>-1</amt_occlusion_kf>
				<amt_border_l>0.0</amt_border_l>
				<amt_border_r>0.0</amt_border_r>
				<amt_border_kf>-1</amt_border_kf>
			</item>
			<!-- frame 60 -->
			<item>
				<tx>16.436427</tx>
				<ty>-0.256009</ty>
				<tz>-0.790380</tz>
				<rx>0.000000</rx>
				<ry>0.000000</ry>
				<rz>-0.014410</rz>
				<state>0</state>
				<occlusion>-1</occlusion>
				<occlusion_kf>-1</occlusion_kf>
				<truncation>-1</truncation>
				<amt_occlusion>0.0</amt_occlusion>
				<amt_occlusion_kf>-1</amt_occlusion_kf>
				<amt_border_l>0.0</amt_border_l>
				<amt_border_r>0.0</amt_border_r>
				<amt_border_kf>-1</amt_border_kf>
			</item>
			<!-- frame 61 -->
			<item>
				<tx>16.210351</tx>
				<ty>-0.251679</ty>
				<tz>-0.781256</tz>
				<rx>0.000000</rx>
				<ry>0.000000</ry>
				<rz>-0.014410</rz>
				<state>0</state>
				<occlusion>-1</occlusion>
				<occlusion_kf>-1</occlusion_kf>
				<truncation>-1</truncation>
				<amt_occlusion>0.0</amt_occlusion>
				<amt_occlusion_kf>-1</amt_occlusion_kf>
				<amt_border_l>0.0</amt_border_l>
				<amt_border_r>0.0</amt_border_r>
				<amt_border_kf>-1</amt_border_kf>
			</item>
			<!-- frame 62 -->
			<item>
				<tx>15.982265</tx>
				<ty>-0.247484</ty>
				<tz>-0.771921</tz>
				<rx>0.000000</rx>
				<ry>0.000000</ry>
				<rz>-0.014410</rz>
				<state>0</state>
				<occlusion>-1</occlusion>
				<occlusion_kf>-1</occlusion_kf>
				<truncation>-1</truncation>
				<amt_occlusion>0.0</amt_occlusion>
				<amt_occlusion_kf>-1</amt_occlusion_kf>
				<amt_border_l>0.0</amt_border_l>
				<amt_border_r>0.0</amt_border_r>
				<amt_border_kf>-1</amt_border_kf>
			</item>
			<!-- frame 63 -->
			<item>
				<tx>15.640798</tx>
				<ty>-0.255696</ty>
				<tz>-0.829216</tz>
				<rx>0.000000</rx>
				<ry>0.000000</ry>
				<rz>-0.007982</rz>
				<state>0</state>
				<occlusion>-1</occlusion>
				<occlusion_kf>-1</occlusion_kf>
				<truncation>-1</truncation>
				<amt_occlusion>0.0</amt_occlusion>
				<amt_occlusion_kf>-1</amt_occlusion_kf>
				<amt_border_l>0.0</amt_border_l>
				<amt_border_r>0.0</amt_border_r>
				<amt_border_kf>-1</amt_border_kf>
			</item>
			<!-- frame 64 -->
			<item>
				<tx>15.380055</tx>
				<ty>-0.252356</ty>
				<tz>-0.823202</tz>
				<rx>0.000000</rx>
				<ry>0.000000</ry>
				<rz>-0.007982</rz>
				<state>0</state>
				<occlusion>-1</occlusion>
				<occlusion_kf>-1</occlusion_kf>
				<truncation>-1</truncation>
				<amt_occlusion>0.0</amt_occlusion>
				<amt_occlusion_kf>-1</amt_occlusion_kf>
				<amt_border_l>0.0</amt_border_l>
				<amt_border_r>0.0</amt_border_r>
				<amt_border_kf>-1</amt_border_kf>
			</item>
			<!-- frame 65 -->
			<item>
				<tx>15.270631</tx>
				<ty>-0.271486</ty>
				<tz>-0.833335</tz>
				<rx>0.000000</rx>
				<ry>0.000000</ry>
				<rz>-0.011223</rz>
				<state>0</state>
				<occlusion>-1</occlusion>
				<occlusion_kf>-1</occlusion_kf>
				<truncation>-1</truncation>
				<amt_occlusion>0.0</amt_occlusion>
				<amt_occlusion_kf>-1</amt_occlusion_kf>
				<amt_border_l>0.0</amt_border_l>
				<amt_border_r>0.0</amt_border_r>
				<amt_border_kf>-1</amt_border_kf>
			</item>
			<!-- frame 66 -->
			<item>
				<tx>15.038431</tx>
				<ty>-0.270061</ty>
				<tz>-0.828459</tz>
				<rx>0.000000</rx>
				<ry>0.000000</ry>
				<rz>-0.011223</rz>
				<state>0</state>
				<occlusion>-1</occlusion>
				<occlusion_kf>-1</occlusion_kf>
				<truncation>-1</truncation>
				<amt_occlusion>0.0</amt_occlusion>
				<amt_occlusion_kf>-1</amt_occlusion_kf>
				<amt_border_l>0.0</amt_border_l>
				<amt_border_r>0.0</amt_border_r>
				<amt_border_kf>-1</amt_border_kf>
			</item>
			<!-- frame 67 -->
			<item>
				<tx>14.892691</tx>
				<ty>-0.229556</ty>
				<tz>-0.837474</tz>
				<rx>0.000000</rx>
				<ry>0.000000</ry>
				<rz>0.001505</rz>
				<state>0</state>
				<occlusion>-1</occlusion>
				<occlusion_kf>-1</occlusion_kf>
				<truncation>-1</truncation>
				<amt_occlusion>0.0</amt_occlusion>
				<amt_occlusion_kf>-1</amt_occlusion_kf>
				<amt_border_l>0.0</amt_border_l>
				<amt_border_r>0.0</amt_border_r>
				<amt_border_kf>-1</amt_border_kf>
			</item>
			<!-- frame 68 -->
			<item>
				<tx>14.672549</tx>
				<ty>-0.225894</ty>
				<tz>-0.833394</tz>
				<rx>0.000000</rx>
				<ry>0.000000</ry>
				<rz>0.001505</rz>
				<state>0</state>
				<occlusion>-1</occlusion>
				<occlusion_kf>-1</occlusion_kf>
				<truncation>-1</truncation>
				<amt_occlusion>0.0</amt_occlusion>
				<amt_occlusion_kf>-1</amt_occlusion_kf>
				<amt_border_l>0.0</amt_border_l>
				<amt_border_r>0.0</amt_border_r>
				<amt_border_kf>-1</amt_border_kf>
			</item>
			<!-- frame 69 -->
			<item>
				<tx>14.438459</tx>
				<ty>-0.222153</ty>
				<tz>-0.829005</tz>
				<rx>0.000000</rx>
				<ry>0.000000</ry>
				<rz>0.001505</rz>
				<state>0</state>
				<occlusion>-1</occlusion>
				<occlusion_kf>-1</occlusion_kf>
				<truncation>-1</truncation>
				<amt_occlusion>0.0</amt_occlusion>
				<amt_occlusion_kf>-1</amt_occlusion_kf>
				<amt_border_l>0.0</amt_border_l>
				<amt_border_r>0.0</amt_border_r>
				<amt_border_kf>-1</amt_border_kf>
			</item>
			<!-- frame 70 -->
			<item>
				<tx>14.318017</tx>
				<ty>-0.181563</ty>
				<tz>-0.805266</tz>
				<rx>0.000000</rx>
				<ry>0.000000</ry>
				<rz>0.005293</rz>
				<state>0</state>
				<occlusion>-1</occlusion>
				<occlusion_kf>-1</occlusion_kf>
				<truncation>-1</truncation>
				<amt_occlusion>0.0</amt_occlusion>
				<amt_occlusion_kf>-1</amt_occlusion_kf>
				<amt_border_l>0.0</amt_border_l>
				<amt_border_r>0.0</amt_border_r>
				<amt_border_kf>-1</amt_border_kf>
			</item>
			<!-- frame 71 -->
			<item>
				<tx>14.107960</tx>
				<ty>-0.176026</ty>
				<tz>-0.799806</tz>
				<rx>0.000000</rx>
				<ry>0.000000</ry>
				<rz>0.005293</rz>
				<state>0</state>
				<occlusion>-1</occlusion>
				<occlusion_kf>-1</occlusion_kf>
				<truncation>-1</truncation>
				<amt_occlusion>0.0</amt_occlusion>
				<amt_occlusion_kf>-1</amt_occlusion_kf>
				<amt_border_l>0.0</amt_border_l>
				<amt_border_r>0.0</amt_border_r>
				<amt_border_kf>-1</amt_border_kf>
			</item>
			<!-- frame 72 -->
			<item>
				<tx>13.948588</tx>
				<ty>-0.177934</ty>
				<tz>-0.782761</tz>
				<rx>0.000000</rx>
				<ry>0.000000</ry>
				<rz>-0.001663</rz>
				<state>0</state>
				<occlusion>-1</occlusion>
				<occlusion_kf>-1</occlusion_kf>
				<truncation>-1</truncation>
				<amt_occlusion>0.0</amt_occlusion>
				<amt_occlusion_kf>-1</amt_occlusion_kf>
				<amt_border_l>0.0</amt_border_l>
				<amt_border_r>0.0</amt_border_r>
				<amt_border_kf>-1</amt_border_kf>
			</item>
			<!-- frame 73 -->
			<item>
				<tx>13.746934</tx>
				<ty>-0.173041</ty>
				<tz>-0.776403</tz>
				<rx>0.000000</rx>
				<ry>0.000000</ry>
				<rz>-0.001663</rz>
				<state>0</state>
				<occlusion>-1</occlusion>
				<occlusion_kf>-1</occlusion_kf>
				<truncation>-1</truncation>
				<amt_occlusion>0.0</amt_occlusion>
				<amt_occlusion_kf>-1</amt_occlusion_kf>
				<amt_border_l>0.0</amt_border_l>
				<amt_border_r>0.0</amt_border_r>
				<amt_border_kf>-1</amt_border_kf>
			</item>
			<!-- frame 74 -->
			<item>
				<tx>13.534620</tx>
				<ty>-0.167974</ty>
				<tz>-0.769578</tz>
				<rx>0.000000</rx>
				<ry>0.000000</ry>
				<rz>-0.001663</rz>
				<state>0</state>
				<occlusion>-1</occlusion>
				<occlusion_kf>-1</occlusion_kf>
				<truncation>-1</truncation>
				<amt_occlusion>0.0</amt_occlusion>
				<amt_occlusion_kf>-1</amt_occlusion_kf>
				<amt_border_l>0.0</amt_border_l>
				<amt_border_r>0.0</amt_border_r>
				<amt_border_kf>-1</amt_border_kf>
			</item>
			<!-- frame 75 -->
			<item>
				<tx>13.375771</tx>
				<ty>-0.165103</ty>
				<tz>-0.770458</tz>
				<rx>0.000000</rx>
				<ry>0.000000</ry>
				<rz>0.001678</rz>
				<state>0</state>
				<occlusion>-1</occlusion>
				<occlusion_kf>-1</occlusion_kf>
				<truncation>-1</truncation>
				<amt_occlusion>0.0</amt_occlusion>
				<amt_occlusion_kf>-1</amt_occlusion_kf>
				<amt_border_l>0.0</amt_border_l>
				<amt_border_r>0.0</amt_border_r>
				<amt_border_kf>-1</amt_border_kf>
			</item>
			<!-- frame 76 -->
			<item>
				<tx>13.180418</tx>
				<ty>-0.160586</ty>
				<tz>-0.764225</tz>
				<rx>0.000000</rx>
				<ry>0.000000</ry>
				<rz>0.001678</rz>
				<state>0</state>
				<occlusion>-1</occlusion>
				<occlusion_kf>-1</occlusion_kf>
				<truncation>-1</truncation>
				<amt_occlusion>0.0</amt_occlusion>
				<amt_occlusion_kf>-1</amt_occlusion_kf>
				<amt_border_l>0.0</amt_border_l>
				<amt_border_r>0.0</amt_border_r>
				<amt_border_kf>-1</amt_border_kf>
			</item>
			<!-- frame 77 -->
			<item>
				<tx>12.795880</tx>
				<ty>-0.042123</ty>
				<tz>-0.810156</tz>
				<rx>0.000000</rx>
				<ry>0.000000</ry>
				<rz>0.010092</rz>
				<state>0</state>
				<occlusion>-1</occlusion>
				<occlusion_kf>-1</occlusion_kf>
				<truncation>-1</truncation>
				<amt_occlusion>0.0</amt_occlusion>
				<amt_occlusion_kf>-1</amt_occlusion_kf>
				<amt_border_l>0.0</amt_border_l>
				<amt_border_r>0.0</amt_border_r>
				<amt_border_kf>-1</amt_border_kf>
			</item>
			<!-- frame 78 -->
			<item>
				<tx>12.573405</tx>
				<ty>-0.030600</ty>
				<tz>-0.807044</tz>
				<rx>0.000000</rx>
				<ry>0.000000</ry>
				<rz>0.010092</rz>
				<state>0</state>
				<occlusion>-1</occlusion>
				<occlusion_kf>-1</occlusion_kf>
				<truncation>-1</truncation>
				<amt_occlusion>0.0</amt_occlusion>
				<amt_occlusion_kf>-1</amt_occlusion_kf>
				<amt_border_l>0.0</amt_border_l>
				<amt_border_r>0.0</amt_border_r>
				<amt_border_kf>-1</amt_border_kf>
			</item>
			<!-- frame 79 -->
			<item>
				<tx>12.524213</tx>
				<ty>-0.060126</ty>
				<tz>-0.777144</tz>
				<rx>0.000000</rx>
				<ry>0.000000</ry>
				<rz>-0.001331</rz>
				<state>0</state>
				<occlusion>-1</occlusion>
				<occlusion_kf>-1</occlusion_kf>
				<truncation>-1</truncation>
				<amt_occlusion>0.0</amt_occlusion>
				<amt_occlusion_kf>-1</amt_occlusion_kf>
				<amt_border_l>0.0</amt_border_l>
				<amt_border_r>0.0</amt_border_r>
				<amt_border_kf>-1</amt_border_kf>
			</item>
			<!-- frame 80 -->
			<item>
				<tx>12.340909</tx>
				<ty>-0.051722</ty>
				<tz>-0.772537</tz>
				<rx>0.000000</rx>
				<ry>0.000000</ry>
				<rz>-0.001331</rz>
				<state>0</state>
				<occlusion>-1</occlusion>
				<occlusion_kf>-1</occlusion_kf>
				<truncation>-1</truncation>
				<amt_occlusion>0.0</amt_occlusion>
				<amt_occlusion_kf>-1</amt_occlusion_kf>
				<amt_border_l>0.0</amt_border_l>
				<amt_border_r>0.0</amt_border_r>
				<amt_border_kf>-1</amt_border_kf>
			</item>
			<!-- frame 81 -->
			<item>
				<tx>12.147563</tx>
				<ty>-0.042812</ty>
				<tz>-0.767600</tz>
				<rx>0.000000</rx>
				<ry>0.000000</ry>
				<rz>-0.001331</rz>
				<state>0</state>
				<occlusion>-1</occlusion>
				<occlusion_kf>-1</occlusion_kf>
				<truncation>-1</truncation>
				<amt_occlusion>0.0</amt_occlusion>
				<amt_occlusion_kf>-1</amt_occlusion_kf>
				<amt_border_l>0.0</amt_border_l>
				<amt_border_r>0.0</amt_border_r>
				<amt_border_kf>-1</amt_border_kf>
			</item>
			<!-- frame 82 -->
			<item>
				<tx>12.182528</tx>
				<ty>-0.196160</ty>
				<tz>-0.738421</tz>
				<rx>0.000000</rx>
				<ry>0.000000</ry>
				<rz>-0.015663</rz>
				<state>0</state>
				<occlusion>-1</occlusion>
				<occlusion_kf>-1</occlusion_kf>
				<truncation>-1</truncation>
				<amt_occlusion>0.0</amt_occlusion>
				<amt_occlusion_kf>-1</amt_occlusion_kf>
				<amt_border_l>0.0</amt_border_l>
				<amt_border_r>0.0</amt_border_r>
				<amt_border_kf>-1</amt_border_kf>
			</item>
			<!-- frame 83 -->
			<item>
				<tx>12.023462</tx>
				<ty>-0.196825</ty>
				<tz>-0.731939</tz>
				<rx>0.000000</rx>
				<ry>0.000000</ry>
				<rz>-0.015663</rz>
				<state>0</state>
				<occlusion>-1</occlusion>
				<occlusion_kf>-1</occlusion_kf>
				<truncation>-1</truncation>
				<amt_occlusion>0.0</amt_occlusion>
				<amt_occlusion_kf>-1</amt_occlusion_kf>
				<amt_border_l>0.0</amt_border_l>
				<amt_border_r>0.0</amt_border_r>
				<amt_border_kf>-1</amt_border_kf>
			</item>
			<!-- frame 84 -->
			<item>
				<tx>11.718107</tx>
				<ty>-0.212903</ty>
				<tz>-0.776197</tz>
				<rx>0.000000</rx>
				<ry>0.000000</ry>
				<rz>0.000554</rz>
				<state>0</state>
				<occlusion>-1</occlusion>
				<occlusion_kf>-1</occlusion_kf>
				<truncation>-1</truncation>
				<amt_occlusion>0.0</amt_occlusion>
				<amt_occlusion_kf>-1</amt_occlusion_kf>
				<amt_border_l>0.0</amt_border_l>
				<amt_border_r>0.0</amt_border_r>
				<amt_border_kf>-1</amt_border_kf>
			</item>
			<!-- frame 85 -->
			<item>
				<tx>11.553250</tx>
				<ty>-0.214824</ty>
				<tz>-0.772965</tz>
				<rx>0.000000</rx>
				<ry>0.000000</ry>
				<rz>0.000554</rz>
				<state>0</state>
				<occlusion>-1</occlusion>
				<occlusion_kf>-1</occlusion_kf>
				<truncation>-1</truncation>
				<amt_occlusion>0.0</amt_occlusion>
				<amt_occlusion_kf>-1</amt_occlusion_kf>
				<amt_border_l>0.0</amt_border_l>
				<amt_border_r>0.0</amt_border_r>
				<amt_border_kf>-1</amt_border_kf>
			</item>
			<!-- frame 86 -->
			<item>
				<tx>11.379852</tx>
				<ty>-0.217082</ty>
				<tz>-0.769521</tz>
				<rx>0.000000</rx>
				<ry>0.000000</ry>
				<rz>0.000554</rz>
				<state>0</state>
				<occlusion>-1</occlusion>
				<occlusion_kf>-1</occlusion_kf>
				<truncation>-1</truncation>
				<amt_occlusion>0.0</amt_occlusion>
				<amt_occlusion_kf>-1</amt_occlusion_kf>
				<amt_border_l>0.0</amt_border_l>
				<amt_border_r>0.0</amt_border_r>
				<amt_border_kf>-1</amt_border_kf>
			</item>
			<!-- frame 87 -->
			<item>
				<tx>11.293840</tx>
				<ty>-0.176820</ty>
				<tz>-0.787216</tz>
				<rx>0.000000</rx>
				<ry>0.000000</ry>
				<rz>-0.001358</rz>
				<state>0</state>
				<occlusion>-1</occlusion>
				<occlusion_kf>-1</occlusion_kf>
				<truncation>-1</truncation>
				<amt_occlusion>0.0</amt_occlusion>
				<amt_occlusion_kf>-1</amt_occlusion_kf>
				<amt_border_l>0.0</amt_border_l>
				<amt_border_r>0.0</amt_border_r>
				<amt_border_kf>-1</amt_border_kf>
			</item>
			<!-- frame 88 -->
			<item>
				<tx>11.134919</tx>
				<ty>-0.177063</ty>
				<tz>-0.784954</tz>
				<rx>0.000000</rx>
				<ry>0.000000</ry>
				<rz>-0.001358</rz>
				<state>0</state>
				<occlusion>-1</occlusion>
				<occlusion_kf>-1</occlusion_kf>
				<truncation>-1</truncation>
				<amt_occlusion>0.0</amt_occlusion>
				<amt_occlusion_kf>-1</amt_occlusion_kf>
				<amt_border_l>0.0</amt_border_l>
				<amt_border_r>0.0</amt_border_r>
				<amt_border_kf>-1</amt_border_kf>
			</item>
			<!-- frame 89 -->
			<item>
				<tx>11.152764</tx>
				<ty>-0.203616</ty>
				<tz>-0.772186</tz>
				<rx>0.000000</rx>
				<ry>0.000000</ry>
				<rz>0.005364</rz>
				<state>0</state>
				<occlusion>-1</occlusion>
				<occlusion_kf>-1</occlusion_kf>
				<truncation>-1</truncation>
				<amt_occlusion>0.0</amt_occlusion>
				<amt_occlusion_kf>-1</amt_occlusion_kf>
				<amt_border_l>0.0</amt_border_l>
				<amt_border_r>0.0</amt_border_r>
				<amt_border_kf>-1</amt_border_kf>
			</item>
			<!-- frame 90 -->
			<item>
				<tx>11.025452</tx>
				<ty>-0.205831</ty>
				<tz>-0.769302</tz>
				<rx>0.000000</rx>
				<ry>0.000000</ry>
				<rz>0.005364</rz>
				<state>0</state>
				<occlusion>-1</occlusion>
				<occlusion_kf>-1</occlusion_kf>
				<truncation>-1</truncation>
				<amt_occlusion>0.0</amt_occlusion>
				<amt_occlusion_kf>-1</amt_occlusion_kf>
				<amt_border_l>0.0</amt_border_l>
				<amt_border_r>0.0</amt_border_r>
				<amt_border_kf>-1</amt_border_kf>
			</item>
			<!-- frame 91 -->
			<item>
				<tx>10.692779</tx>
				<ty>-0.213619</ty>
				<tz>-0.806669</tz>
				<rx>0.000000</rx>
				<ry>0.000000</ry>
				<rz>0.003249</rz>
				<state>0</state>
				<occlusion>-1</occlusion>
				<occlusion_kf>-1</occlusion_kf>
				<truncation>-1</truncation>
				<amt_occlusion>0.0</amt_occlusion>
				<amt_occlusion_kf>-1</amt_occlusion_kf>
				<amt_border_l>0.0</amt_border_l>
				<amt_border_r>0.0</amt_border_r>
				<amt_border_kf>-1</amt_border_kf>
			</item>
			<!-- frame 92 -->
			<item>
				<tx>10.539541</tx>
				<ty>-0.216601</ty>
				<tz>-0.806391</tz>
				<rx>0.000000</rx>
				<ry>0.000000</ry>
				<rz>0.003249</rz>
				<state>0</state>
				<occlusion>-1</occlusion>
				<occlusion_kf>-1</occlusion_kf>
				<truncation>-1</truncation>
				<amt_occlusion>0.0</amt_occlusion>
				<amt_occlusion_kf>-1</amt_occlusion_kf>
				<amt_border_l>0.0</amt_border_l>
				<amt_border_r>0.0</amt_border_r>
				<amt_border_kf>-1</amt_border_kf>
			</item>
			<!-- frame 93 -->
			<item>
				<tx>10.388439</tx>
				<ty>-0.219792</ty>
				<tz>-0.806168</tz>
				<rx>0.000000</rx>
				<ry>0.000000</ry>
				<rz>0.003249</rz>
				<state>0</state>
				<occlusion>-1</occlusion>
				<occlusion_kf>-1</occlusion_kf>
				<truncation>-1</truncation>
				<amt_occlusion>0.0</amt_occlusion>
				<amt_occlusion_kf>-1</amt_occlusion_kf>
				<amt_border_l>0.0</amt_border_l>
				<amt_border_r>0.0</amt_border_r>
				<amt_border_kf>-1</amt_border_kf>
			</item>
			<!-- frame 94 -->
			<item>
				<tx>10.304856</tx>
				<ty>-0.186035</ty>
				<tz>-0.834048</tz>
				<rx>0.000000</rx>
				<ry>0.000000</ry>
				<rz>0.015335</rz>
				<state>0</state>
				<occlusion>-1</occlusion>
				<occlusion_kf>-1</occlusion_kf>
				<truncation>-1</truncation>
				<amt_occlusion>0.0</amt_occlusion>
				<amt_occlusion_kf>-1</amt_occlusion_kf>
				<amt_border_l>0.0</amt_border_l>
				<amt_border_r>0.0</amt_border_r>
				<amt_border_kf>-1</amt_border_kf>
			</item>
			<!-- frame 95 -->
			<item>
				<tx>10.166233</tx>
				<ty>-0.187497</ty>
				<tz>-0.835575</tz>
				<rx>0.000000</rx>
				<ry>0.000000</ry>
				<rz>0.015335</rz>
				<state>0</state>
				<occlusion>-1</occlusion>
				<occlusion_kf>-1</occlusion_kf>
				<truncation>-1</truncation>
				<amt_occlusion>0.0</amt_occlusion>
				<amt_occlusion_kf>-1</amt_occlusion_kf>
				<amt_border_l>0.0</amt_border_l>
				<amt_border_r>0.0</amt_border_r>
				<amt_border_kf>-1</amt_border_kf>
			</item>
			<!-- frame 96 -->
			<item>
				<tx>9.787982</tx>
				<ty>-0.210497</ty>
				<tz>-0.907505</tz>
				<rx>0.000000</rx>
				<ry>0.000000</ry>
				<rz>0.066870</rz>
				<state>0</state>
				<occlusion>-1</occlusion>
				<occlusion_kf>-1</occlusion_kf>
				<truncation>-1</truncation>
				<amt_occlusion>0.0</amt_occlusion>
				<amt_occlusion_kf>-1</amt_occlusion_kf>
				<amt_border_l>0.0</amt_border_l>
				<amt_border_r>0.0</amt_border_r>
				<amt_border_kf>-1</amt_border_kf>
			</item>
			<!-- frame 97 -->
			<item>
				<tx>9.616721</tx>
				<ty>-0.213634</ty>
				<tz>-0.913609</tz>
				<rx>0.000000</rx>
				<ry>0.000000</ry>
				<rz>0.066870</rz>
				<state>0</state>
				<occlusion>-1</occlusion>
				<occlusion_kf>-1</occlusion_kf>
				<truncation>-1</truncation>
				<amt_occlusion>0.0</amt_occlusion>
				<amt_occlusion_kf>-1</amt_occlusion_kf>
				<amt_border_l>0.0</amt_border_l>
				<amt_border_r>0.0</amt_border_r>
				<amt_border_kf>-1</amt_border_kf>
			</item>
			<!-- frame 98 -->
			<item>
				<tx>9.445784</tx>
				<ty>-0.216966</ty>
				<tz>-0.919893</tz>
				<rx>0.000000</rx>
				<ry>0.000000</ry>
				<rz>0.066870</rz>
				<state>0</state>
				<occlusion>-1</occlusion>
				<occlusion_kf>-1</occlusion_kf>
				<truncation>-1</truncation>
				<amt_occlusion>0.0</amt_occlusion>
				<amt_occlusion_kf>-1</amt_occlusion_kf>
				<amt_border_l>0.0</amt_border_l>
				<amt_border_r>0.0</amt_border_r>
				<amt_border_kf>-1</amt_border_kf>
			</item>
			<!-- frame 99 -->
			<item>
				<tx>9.510287</tx>
				<ty>-0.241669</ty>
				<tz>-0.910988</tz>
				<rx>0.000000</rx>
				<ry>0.000000</ry>
				<rz>0.037325</rz>
				<state>0</state>
				<occlusion>-1</occlusion>
				<occlusion_kf>-1</occlusion_kf>
				<truncation>-1</truncation>
				<amt_occlusion>0.0</amt_occlusion>
				<amt_occlusion_kf>-1</amt_occlusion_kf>
				<amt_border_l>0.0</amt_border_l>
				<amt_border_r>0.0</amt_border_r>
				<amt_border_kf>-1</amt_border_kf>
			</item>
			<!-- frame 100 -->
			<item>
				<tx>9.372773</tx>
				<ty>-0.246616</ty>
				<tz>-0.916766</tz>
				<rx>0.000000</rx>
				<ry>0.000000</ry>
				<rz>0.037325</rz>
				<state>0</state>
				<occlusion>-1</occlusion>
				<occlusion_kf>-1</occlusion_kf>
				<truncation>-1</truncation>
				<amt_occlusion>0.0</amt_occlusion>
				<amt_occlusion_kf>-1</amt_occlusion_kf>
				<amt_border_l>0.0</amt_border_l>
				<amt_border_r>0.0</amt_border_r>
				<amt_border_kf>-1</amt_border_kf>
			</item>
			<!-- frame 101 -->
			<item>
				<tx>9.532421</tx>
				<ty>-0.225386</ty>
				<tz>-0.887534</tz>
				<rx>0.000000</rx>
				<ry>0.000000</ry>
				<rz>0.009198</rz>
				<state>0</state>
				<occlusion>-1</occlusion>
				<occlusion_kf>-1</occlusion_kf>
				<truncation>-1</truncation>
				<amt_occlusion>0.0</amt_occlusion>
				<amt_occlusion_kf>-1</amt_occlusion_kf>
				<amt_border_l>0.0</amt_border_l>
				<amt_border_r>0.0</amt_border_r>
				<amt_border_kf>-1</amt_border_kf>
			</item>
			<!-- frame 102 -->
			<item>
				<tx>9.444026</tx>
				<ty>-0.229147</ty>
				<tz>-0.891466</tz>
				<rx>0.000000</rx>
				<ry>0.000000</ry>
				<rz>0.009198</rz>
				<state>0</state>
				<occlusion>-1</occlusion>
				<occlusion_kf>-1</occlusion_kf>
				<truncation>-1</truncation>
				<amt_occlusion>0.0</amt_occlusion>
				<amt_occlusion_kf>-1</amt_occlusion_kf>
				<amt_border_l>0.0</amt_border_l>
				<amt_border_r>0.0</amt_border_r>
				<amt_border_kf>-1</amt_border_kf>
			</item>
			<!-- frame 103 -->
			<item>
				<tx>9.452261</tx>
				<ty>-0.186736</ty>
				<tz>-0.879429</tz>
				<rx>0.000000</rx>
				<ry>0.000000</ry>
				<rz>0.040099</rz>
				<state>0</state>
				<occlusion>-1</occlusion>
				<occlusion_kf>-1</occlusion_kf>
				<truncation>-1</truncation>
				<amt_occlusion>0.0</amt_occlusion>
				<amt_occlusion_kf>-1</amt_occlusion_kf>
				<amt_border_l>0.0</amt_border_l>
				<amt_border_r>0.0</amt_border_r>
				<amt_border_kf>-1</amt_border_kf>
			</item>
			<!-- frame 104 -->
			<item>
				<tx>9.387850</tx>
				<ty>-0.187884</ty>
				<tz>-0.882554</tz>
				<rx>0.000000</rx>
				<ry>0.000000</ry>
				<rz>0.040099</rz>
				<state>0</state>
				<occlusion>-1</occlusion>
				<occlusion_kf>-1</occlusion_kf>
				<truncation>-1</truncation>
				<amt_occlusion>0.0</amt_occlusion>
				<amt_occlusion_kf>-1</amt_occlusion_kf>
				<amt_border_l>0.0</amt_border_l>
				<amt_border_r>0.0</amt_border_r>
				<amt_border_kf>-1</amt_border_kf>
			</item>
			<!-- frame 105 -->
			<item>
				<tx>9.328456</tx>
				<ty>-0.189165</ty>
				<tz>-0.885797</tz>
				<rx>0.000000</rx>
				<ry>0.000000</ry>
				<rz>0.040099</rz>
				<state>0</state>
				<occlusion>-1</occlusion>
				<occlusion_kf>-1</occlusion_kf>
				<truncation>-1</truncation>
				<amt_occlusion>0.0</amt_occlusion>
				<amt_occlusion_kf>-1</amt_occlusion_kf>
				<amt_border_l>0.0</amt_border_l>
				<amt_border_r>0.0</amt_border_r>
				<amt_border_kf>-1</amt_border_kf>
			</item>
			<!-- frame 106 -->
			<item>
				<tx>9.320865</tx>
				<ty>-0.092178</ty>
				<tz>-0.851526</tz>
				<rx>0.000000</rx>
				<ry>0.000000</ry>
				<rz>0.080599</rz>
				<state>0</state>
				<occlusion>-1</occlusion>
				<occlusion_kf>-1</occlusion_kf>
				<truncation>-1</truncation>
				<amt_occlusion>0.0</amt_occlusion>
				<amt_occlusion_kf>-1</amt_occlusion_kf>
				<amt_border_l>0.0</amt_border_l>
				<amt_border_r>0.0</amt_border_r>
				<amt_border_kf>-1</amt_border_kf>
			</item>
			<!-- frame 107 -->
			<item>
				<tx>9.279178</tx>
				<ty>-0.087981</ty>
				<tz>-0.852764</tz>
				<rx>0.000000</rx>
				<ry>0.000000</ry>
				<rz>0.080599</rz>
				<state>0</state>
				<occlusion>-1</occlusion>
				<occlusion_kf>-1</occlusion_kf>
				<truncation>-1</truncation>
				<amt_occlusion>0.0</amt_occlusion>
				<amt_occlusion_kf>-1</amt_occlusion_kf>
				<amt_border_l>0.0</amt_border_l>
				<amt_border_r>0.0</amt_border_r>
				<amt_border_kf>-1</amt_border_kf>
			</item>
			<!-- frame 108 -->
			<item>
				<tx>9.134666</tx>
				<ty>-0.135649</ty>
				<tz>-0.846328</tz>
				<rx>0.000000</rx>
				<ry>0.000000</ry>
				<rz>0.098404</rz>
				<state>0</state>
				<occlusion>-1</occlusion>
				<occlusion_kf>-1</occlusion_kf>
				<truncation>-1</truncation>
				<amt_occlusion>0.0</amt_occlusion>
				<amt_occlusion_kf>-1</amt_occlusion_kf>
				<amt_border_l>0.0</amt_border_l>
				<amt_border_r>0.0</amt_border_r>
				<amt_border_kf>-1</amt_border_kf>
			</item>
			<!-- frame 109 -->
			<item>
				<tx>9.087793</tx>
				<ty>-0.134688</ty>
				<tz>-0.847183</tz>
				<rx>0.000000</rx>
				<ry>0.000000</ry>
				<rz>0.098404</rz>
				<state>0</state>
				<occlusion>-1</occlusion>
				<occlusion_kf>-1</occlusion_kf>
				<truncation>-1</truncation>
				<amt_occlusion>0.0</amt_occlusion>
				<amt_occlusion_kf>-1</amt_occlusion_kf>
				<amt_border_l>0.0</amt_border_l>
				<amt_border_r>0.0</amt_border_r>
				<amt_border_kf>-1</amt_border_kf>
			</item>
			<!-- frame 110 -->
			<item>
				<tx>9.045840</tx>
				<ty>-0.133800</ty>
				<tz>-0.848074</tz>
				<rx>0.000000</rx>
				<ry>0.000000</ry>
				<rz>0.098404</rz>
				<state>0</state>
				<occlusion>-1</occlusion>
				<occlusion_kf>-1</occlusion_kf>
				<truncation>-1</truncation>
				<amt_occlusion>0.0</amt_occlusion>
				<amt_occlusion_kf>-1</amt_occlusion_kf>
				<amt_border_l>0.0</amt_border_l>
				<amt_border_r>0.0</amt_border_r>
				<amt_border_kf>-1</amt_border_kf>
			</item>
			<!-- frame 111 -->
			<item>
				<tx>8.981743</tx>
				<ty>-0.225503</ty>
				<tz>-0.864540</tz>
				<rx>0.000000</rx>
				<ry>0.000000</ry>
				<rz>0.011200</rz>
				<state>0</state>
				<occlusion>-1</occlusion>
				<occlusion_kf>-1</occlusion_kf>
				<truncation>-1</truncation>
				<amt_occlusion>0.0</amt_occlusion>
				<amt_occlusion_kf>-1</amt_occlusion_kf>
				<amt_border_l>0.0</amt_border_l>
				<amt_border_r>0.0</amt_border_r>
				<amt_border_kf>-1</amt_border_kf>
			</item>
			<!-- frame 112 -->
			<item>
				<tx>8.945525</tx>
				<ty>-0.230040</ty>
				<tz>-0.866399</tz>
				<rx>0.000000</rx>
				<ry>0.000000</ry>
				<rz>0.011200</rz>
				<state>0</state>
				<occlusion>-1</occlusion>
				<occlusion_kf>-1</occlusion_kf>
				<truncation>-1</truncation>
				<amt_occlusion>0.0</amt_occlusion>
				<amt_occlusion_kf>-1</amt_occlusion_kf>
				<amt_border_l>0.0</amt_border_l>
				<amt_border_r>0.0</amt_border_r>
				<amt_border_kf>-1</amt_border_kf>
			</item>
			<!-- frame 113 -->
			<item>
				<tx>8.716958</tx>
				<ty>-0.260134</ty>
				<tz>-0.872158</tz>
				<rx>0.000000</rx>
				<ry>0.000000</ry>
				<rz>0.003981</rz>
				<state>0</state>
				<occlusion>-1</occlusion>
				<occlusion_kf>-1</occlusion_kf>
				<truncation>-1</truncation>
				<amt_occlusion>0.0</amt_occlusion>
				<amt_occlusion_kf>-1</amt_occlusion_kf>
				<amt_border_l>0.0</amt_border_l>
				<amt_border_r>0.0</amt_border_r>
				<amt_border_kf>-1</amt_border_kf>
			</item>
			<!-- frame 114 -->
			<item>
				<tx>8.659816</tx>
				<ty>-0.266615</ty>
				<tz>-0.874374</tz>
				<rx>0.000000</rx>
				<ry>0.000000</ry>
				<rz>0.003981</rz>
				<state>0</state>
				<occlusion>-1</occlusion>
				<occlusion_kf>-1</occlusion_kf>
				<truncation>-1</truncation>
				<amt_occlusion>0.0</amt_occlusion>
				<amt_occlusion_kf>-1</amt_occlusion_kf>
				<amt_border_l>0.0</amt_border_l>
				<amt_border_r>0.0</amt_border_r>
				<amt_border_kf>-1</amt_border_kf>
			</item>
			<!-- frame 115 -->
			<item>
				<tx>8.605173</tx>
				<ty>-0.231703</ty>
				<tz>-0.906848</tz>
				<rx>0.000000</rx>
				<ry>0.000000</ry>
				<rz>0.069422</rz>
				<state>0</state>
				<occlusion>-1</occlusion>
				<occlusion_kf>-1</occlusion_kf>
				<truncation>-1</truncation>
				<amt_occlusion>0.0</amt_occlusion>
				<amt_occlusion_kf>-1</amt_occlusion_kf>
				<amt_border_l>0.0</amt_border_l>
				<amt_border_r>0.0</amt_border_r>
				<amt_border_kf>-1</amt_border_kf>
			</item>
			<!-- frame 116 -->
			<item>
				<tx>8.553771</tx>
				<ty>-0.235942</ty>
				<tz>-0.911140</tz>
				<rx>0.000000</rx>
				<ry>0.000000</ry>
				<rz>0.069422</rz>
				<state>0</state>
				<occlusion>-1</occlusion>
				<occlusion_kf>-1</occlusion_kf>
				<truncation>-1</truncation>
				<amt_occlusion>0.0</amt_occlusion>
				<amt_occlusion_kf>-1</amt_occlusion_kf>
				<amt_border_l>0.0</amt_border_l>
				<amt_border_r>0.0</amt_border_r>
				<amt_border_kf>-1</amt_border_kf>
			</item>
			<!-- frame 117 -->
			<item>
				<tx>8.505562</tx>
				<ty>-0.240315</ty>
				<tz>-0.915511</tz>
				<rx>0.000000</rx>
				<ry>0.000000</ry>
				<rz>0.069422</rz>
				<state>0</state>
				<occlusion>-1</occlusion>
				<occlusion_kf>-1</occlusion_kf>
				<truncation>-1</truncation>
				<amt_occlusion>0.0</amt_occlusion>
				<amt_occlusion_kf>-1</amt_occlusion_kf>
				<amt_border_l>0.0</amt_border_l>
				<amt_border_r>0.0</amt_border_r>
				<amt_border_kf>-1</amt_border_kf>
			</item>
			<!-- frame 118 -->
			<item>
				<tx>8.546683</tx>
				<ty>-0.184202</ty>
				<tz>-0.904171</tz>
				<rx>0.000000</rx>
				<ry>0.000000</ry>
				<rz>0.070117</rz>
				<state>0</state>
				<occlusion>-1</occlusion>
				<occlusion_kf>-1</occlusion_kf>
				<truncation>-1</truncation>
				<amt_occlusion>0.0</amt_occlusion>
				<amt_occlusion_kf>-1</amt_occlusion_kf>
				<amt_border_l>0.0</amt_border_l>
				<amt_border_r>0.0</amt_border_r>
				<amt_border_kf>-1</amt_border_kf>
			</item>
			<!-- frame 119 -->
			<item>
				<tx>8.516579</tx>
				<ty>-0.185389</ty>
				<tz>-0.907845</tz>
				<rx>0.000000</rx>
				<ry>0.000000</ry>
				<rz>0.070117</rz>
				<state>0</state>
				<occlusion>-1</occlusion>
				<occlusion_kf>-1</occlusion_kf>
				<truncation>-1</truncation>
				<amt_occlusion>0.0</amt_occlusion>
				<amt_occlusion_kf>-1</amt_occlusion_kf>
				<amt_border_l>0.0</amt_border_l>
				<amt_border_r>0.0</amt_border_r>
				<amt_border_kf>-1</amt_border_kf>
			</item>
			<!-- frame 120 -->
			<item>
				<tx>8.533503</tx>
				<ty>-0.142882</ty>
				<tz>-0.893750</tz>
				<rx>0.000000</rx>
				<ry>0.000000</ry>
				<rz>0.093691</rz>
				<state>0</state>
				<occlusion>-1</occlusion>
				<occlusion_kf>-1</occlusion_kf>
				<truncation>-1</truncation>
				<amt_occlusion>0.0</amt_occlusion>
				<amt_occlusion_kf>-1</amt_occlusion_kf>
				<amt_border_l>0.0</amt_border_l>
				<amt_border_r>0.0</amt_border_r>
				<amt_border_kf>-1</amt_border_kf>
			</item>
			<!-- frame 121 -->
			<item>
				<tx>8.517284</tx>
				<ty>-0.141516</ty>
				<tz>-0.896494</tz>
				<rx>0.000000</rx>
				<ry>0.000000</ry>
				<rz>0.093691</rz>
				<state>0</state>
				<occlusion>-1</occlusion>
				<occlusion_kf>-1</occlusion_kf>
				<truncation>-1</truncation>
				<amt_occlusion>0.0</amt_occlusion>
				<amt_occlusion_kf>-1</amt_occlusion_kf>
				<amt_border_l>0.0</amt_border_l>
				<amt_border_r>0.0</amt_border_r>
				<amt_border_kf>-1</amt_border_kf>
			</item>
			<!-- frame 122 -->
			<item>
				<tx>8.505079</tx>
				<ty>-0.140177</ty>
				<tz>-0.899295</tz>
				<rx>0.000000</rx>
				<ry>0.000000</ry>
				<rz>0.093691</rz>
				<state>0</state>
				<occlusion>-1</occlusion>
				<occlusion_kf>-1</occlusion_kf>
				<truncation>-1</truncation>
				<amt_occlusion>0.0</amt_occlusion>
				<amt_occlusion_kf>-1</amt_occlusion_kf>
				<amt_border_l>0.0</amt_border_l>
				<amt_border_r>0.0</amt_border_r>
				<amt_border_kf>-1</amt_border_kf>
			</item>
			<!-- frame 123 -->
			<item>
				<tx>8.523075</tx>
				<ty>-0.072864</ty>
				<tz>-0.908922</tz>
				<rx>0.000000</rx>
				<ry>0.000000</ry>
				<rz>0.121105</rz>
				<state>0</state>
				<occlusion>-1</occlusion>
				<occlusion_kf>-1</occlusion_kf>
				<truncation>-1</truncation>
				<amt_occlusion>0.0</amt_occlusion>
				<amt_occlusion_kf>-1</amt_occlusion_kf>
				<amt_border_l>0.0</amt_border_l>
				<amt_border_r>0.0</amt_border_r>
				<amt_border_kf>-1</amt_border_kf>
			</item>
			<!-- frame 124 -->
			<item>
				<tx>8.522552</tx>
				<ty>-0.067812</ty>
				<tz>-0.912233</tz>
				<rx>0.000000</rx>
				<ry>0.000000</ry>
				<rz>0.121105</rz>
				<state>0</state>
				<occlusion>-1</occlusion>
				<occlusion_kf>-1</occlusion_kf>
				<truncation>-1</truncation>
				<amt_occlusion>0.0</amt_occlusion>
				<amt_occlusion_kf>-1</amt_occlusion_kf>
				<amt_border_l>0.0</amt_border_l>
				<amt_border_r>0.0</amt_border_r>
				<amt_border_kf>-1</amt_border_kf>
			</item>
			<!-- frame 125 -->
			<item>
				<tx>8.514039</tx>
				<ty>-0.083908</ty>
				<tz>-0.919365</tz>
				<rx>0.000000</rx>
				<ry>0.000000</ry>
				<rz>0.079233</rz>
				<state>0</state>
				<occlusion>-1</occlusion>
				<occlusion_kf>-1</occlusion_kf>
				<truncation>-1</truncation>
				<amt_occlusion>0.0</amt_occlusion>
				<amt_occlusion_kf>-1</amt_occlusion_kf>
				<amt_border_l>0.0</amt_border_l>
				<amt_border_r>0.0</amt_border_r>
				<amt_border_kf>-1</amt_border_kf>
			</item>
			<!-- frame 126 -->
			<item>
				<tx>8.520050</tx>
				<ty>-0.080055</ty>
				<tz>-0.923046</tz>
				<rx>0.000000</rx>
				<ry>0.000000</ry>
				<rz>0.079233</rz>
				<state>0</state>
				<occlusion>-1</occlusion>
				<occlusion_kf>-1</occlusion_kf>
				<truncation>-1</truncation>
				<amt_occlusion>0.0</amt_occlusion>
				<amt_occlusion_kf>-1</amt_occlusion_kf>
				<amt_border_l>0.0</amt_border_l>
				<amt_border_r>0.0</amt_border_r>
				<amt_border_kf>-1</amt_border_kf>
			</item>
			<!-- frame 127 -->
			<item>
				<tx>8.650039</tx>
				<ty>-0.106813</ty>
				<tz>-0.883432</tz>
				<rx>0.000000</rx>
				<ry>0.000000</ry>
				<rz>0.029266</rz>
				<state>0</state>
				<occlusion>-1</occlusion>
				<occlusion_kf>-1</occlusion_kf>
				<truncation>-1</truncation>
				<amt_occlusion>0.0</amt_occlusion>
				<amt_occlusion_kf>-1</amt_occlusion_kf>
				<amt_border_l>0.0</amt_border_l>
				<amt_border_r>0.0</amt_border_r>
				<amt_border_kf>-1</amt_border_kf>
			</item>
			<!-- frame 128 -->
			<item>
				<tx>8.683406</tx>
				<ty>-0.104876</ty>
				<tz>-0.884474</tz>
				<rx>0.000000</rx>
				<ry>0.000000</ry>
				<rz>0.029266</rz>
				<state>0</state>
				<occlusion>-1</occlusion>
				<occlusion_kf>-1</occlusion_kf>
				<truncation>-1</truncation>
				<amt_occlusion>0.0</amt_occlusion>
				<amt_occlusion_kf>-1</amt_occlusion_kf>
				<amt_border_l>0.0</amt_border_l>
				<amt_border_r>0.0</amt_border_r>
				<amt_border_kf>-1</amt_border_kf>
			</item>
			<!-- frame 129 -->
			<item>
				<tx>8.722100</tx>
				<ty>-0.102950</ty>
				<tz>-0.885533</tz>
				<rx>0.000000</rx>
				<ry>0.000000</ry>
				<rz>0.029266</rz>
				<state>0</state>
				<occlusion>-1</occlusion>
				<occlusion_kf>-1</occlusion_kf>
				<truncation>-1</truncation>
				<amt_occlusion>0.0</amt_occlusion>
				<amt_occlusion_kf>-1</amt_occlusion_kf>
				<amt_border_l>0.0</amt_border_l>
				<amt_border_r>0.0</amt_border_r>
				<amt_border_kf>-1</amt_border_kf>
			</item>
			<!-- frame 130 -->
			<item>
				<tx>8.590968</tx>
				<ty>-0.103374</ty>
				<tz>-0.905602</tz>
				<rx>0.000000</rx>
				<ry>0.000000</ry>
				<rz>0.069291</rz>
				<state>0</state>
				<occlusion>-1</occlusion>
				<occlusion_kf>-1</occlusion_kf>
				<truncation>-1</truncation>
				<amt_occlusion>0.0</amt_occlusion>
				<amt_occlusion_kf>-1</amt_occlusion_kf>
				<amt_border_l>0.0</amt_border_l>
				<amt_border_r>0.0</amt_border_r>
				<amt_border_kf>-1</amt_border_kf>
			</item>
			<!-- frame 131 -->
			<item>
				<tx>8.616305</tx>
				<ty>-0.101521</ty>
				<tz>-0.907916</tz>
				<rx>0.000000</rx>
				<ry>0.000000</ry>
				<rz>0.069291</rz>
				<state>0</state>
				<occlusion>-1</occlusion>
				<occlusion_kf>-1</occlusion_kf>
				<truncation>-1</truncation>
				<amt_occlusion>0.0</amt_occlusion>
				<amt_occlusion_kf>-1</amt_occlusion_kf>
				<amt_border_l>0.0</amt_border_l>
				<amt_border_r>0.0</amt_border_r>
				<amt_border_kf>-1</amt_border_kf>
			</item>
			<!-- frame 132 -->
			<item>
				<tx>8.597264</tx>
				<ty>-0.053698</ty>
				<tz>-0.900161</tz>
				<rx>0.000000</rx>
				<ry>0.000000</ry>
				<rz>0.098739</rz>
				<state>0</state>
				<occlusion>-1</occlusion>
				<occlusion_kf>-1</occlusion_kf>
				<truncation>-1</truncation>
				<amt_occlusion>0.0</amt_occlusion>
				<amt_occlusion_kf>-1</amt_occlusion_kf>
				<amt_border_l>0.0</amt_border_l>
				<amt_border_r>0.0</amt_border_r>
				<amt_border_kf>-1</amt_border_kf>
			</item>
			<!-- frame 133 -->
			<item>
				<tx>8.621667</tx>
				<ty>-0.049118</ty>
				<tz>-0.901809</tz>
				<rx>0.000000</rx>
				<ry>0.000000</ry>
				<rz>0.098739</rz>
				<state>0</state>
				<occlusion>-1</occlusion>
				<occlusion_kf>-1</occlusion_kf>
				<truncation>-1</truncation>
				<amt_occlusion>0.0</amt_occlusion>
				<amt_occlusion_kf>-1</amt_occlusion_kf>
				<amt_border_l>0.0</amt_border_l>
				<amt_border_r>0.0</amt_border_r>
				<amt_border_kf>-1</amt_border_kf>
			</item>
			<!-- frame 134 -->
			<item>
				<tx>8.649529</tx>
				<ty>-0.044484</ty>
				<tz>-0.903487</tz>
				<rx>0.000000</rx>
				<ry>0.000000</ry>
				<rz>0.098739</rz>
				<state>0</state>
				<occlusion>-1</occlusion>
				<occlusion_kf>-1</occlusion_kf>
				<truncation>-1</truncation>
				<amt_occlusion>0.0</amt_occlusion>
				<amt_occlusion_kf>-1</amt_occlusion_kf>
				<amt_border_l>0.0</amt_border_l>
				<amt_border_r>0.0</amt_border_r>
				<amt_border_kf>-1</amt_border_kf>
			</item>
			<!-- frame 135 -->
			<item>
				<tx>8.590350</tx>
				<ty>-0.084919</ty>
				<tz>-0.917467</tz>
				<rx>0.000000</rx>
				<ry>0.000000</ry>
				<rz>0.027319</rz>
				<state>0</state>
				<occlusion>-1</occlusion>
				<occlusion_kf>-1</occlusion_kf>
				<truncation>-1</truncation>
				<amt_occlusion>0.0</amt_occlusion>
				<amt_occlusion_kf>-1</amt_occlusion_kf>
				<amt_border_l>0.0</amt_border_l>
				<amt_border_r>0.0</amt_border_r>
				<amt_border_kf>-1</amt_border_kf>
			</item>
			<!-- frame 136 -->
			<item>
				<tx>8.613560</tx>
				<ty>-0.082649</ty>
				<tz>-0.920039</tz>
				<rx>0.000000</rx>
				<ry>0.000000</ry>
				<rz>0.027319</rz>
				<state>0</state>
				<occlusion>-1</occlusion>
				<occlusion_kf>-1</occlusion_kf>
				<truncation>-1</truncation>
				<amt_occlusion>0.0</amt_occlusion>
				<amt_occlusion_kf>-1</amt_occlusion_kf>
				<amt_border_l>0.0</amt_border_l>
				<amt_border_r>0.0</amt_border_r>
				<amt_border_kf>-1</amt_border_kf>
			</item>
			<!-- frame 137 -->
			<item>
				<tx>8.587503</tx>
				<ty>-0.103590</ty>
				<tz>-0.927916</tz>
				<rx>0.000000</rx>
				<ry>0.000000</ry>
				<rz>0.040138</rz>
				<state>0</state>
				<occlusion>-1</occlusion>
				<occlusion_kf>-1</occlusion_kf>
				<truncation>-1</truncation>
				<amt_occlusion>0.0</amt_occlusion>
				<amt_occlusion_kf>-1</amt_occlusion_kf>
				<amt_border_l>0.0</amt_border_l>
				<amt_border_r>0.0</amt_border_r>
				<amt_border_kf>-1</amt_border_kf>
			</item>
			<!-- frame 138 -->
			<item>
				<tx>8.607141</tx>
				<ty>-0.102885</ty>
				<tz>-0.930761</tz>
				<rx>0.000000</rx>
				<ry>0.000000</ry>
				<rz>0.040138</rz>
				<state>0</state>
				<occlusion>-1</occlusion>
				<occlusion_kf>-1</occlusion_kf>
				<truncation>-1</truncation>
				<amt_occlusion>0.0</amt_occlusion>
				<amt_occlusion_kf>-1</amt_occlusion_kf>
				<amt_border_l>0.0</amt_border_l>
				<amt_border_r>0.0</amt_border_r>
				<amt_border_kf>-1</amt_border_kf>
			</item>
			<!-- frame 139 -->
			<item>
				<tx>8.580265</tx>
				<ty>-0.037573</ty>
				<tz>-0.919564</tz>
				<rx>0.000000</rx>
				<ry>0.000000</ry>
				<rz>0.091095</rz>
				<state>0</state>
				<occlusion>-1</occlusion>
				<occlusion_kf>-1</occlusion_kf>
				<truncation>-1</truncation>
				<amt_occlusion>0.0</amt_occlusion>
				<amt_occlusion_kf>-1</amt_occlusion_kf>
				<amt_border_l>0.0</amt_border_l>
				<amt_border_r>0.0</amt_border_r>
				<amt_border_kf>-1</amt_border_kf>
			</item>
			<!-- frame 140 -->
			<item>
				<tx>8.596618</tx>
				<ty>-0.032792</ty>
				<tz>-0.921599</tz>
				<rx>0.000000</rx>
				<ry>0.000000</ry>
				<rz>0.091095</rz>
				<state>0</state>
				<occlusion>-1</occlusion>
				<occlusion_kf>-1</occlusion_kf>
				<truncation>-1</truncation>
				<amt_occlusion>0.0</amt_occlusion>
				<amt_occlusion_kf>-1</amt_occlusion_kf>
				<amt_border_l>0.0</amt_border_l>
				<amt_border_r>0.0</amt_border_r>
				<amt_border_kf>-1</amt_border_kf>
			</item>
			<!-- frame 141 -->
			<item>
				<tx>8.615857</tx>
				<ty>-0.027686</ty>
				<tz>-0.923780</tz>
				<rx>0.000000</rx>
				<ry>0.000000</ry>
				<rz>0.091095</rz>
				<state>0</state>
				<occlusion>-1</occlusion>
				<occlusion_kf>-1</occlusion_kf>
				<truncation>-1</truncation>
				<amt_occlusion>0.0</amt_occlusion>
				<amt_occlusion_kf>-1</amt_occlusion_kf>
				<amt_border_l>0.0</amt_border_l>
				<amt_border_r>0.0</amt_border_r>
				<amt_border_kf>-1</amt_border_kf>
			</item>
			<!-- frame 142 -->
			<item>
				<tx>8.588819</tx>
				<ty>-0.080191</ty>
				<tz>-0.915915</tz>
				<rx>0.000000</rx>
				<ry>0.000000</ry>
				<rz>0.034321</rz>
				<state>0</state>
				<occlusion>-1</occlusion>
				<occlusion_kf>-1</occlusion_kf>
				<truncation>-1</truncation>
				<amt_occlusion>0.0</amt_occlusion>
				<amt_occlusion_kf>-1</amt_occlusion_kf>
				<amt_border_l>0.0</amt_border_l>
				<amt_border_r>0.0</amt_border_r>
				<amt_border_kf>-1</amt_border_kf>
			</item>
			<!-- frame 143 -->
			<item>
				<tx>8.603964</tx>
				<ty>-0.078579</ty>
				<tz>-0.917463</tz>
				<rx>0.000000</rx>
				<ry>0.000000</ry>
				<rz>0.034321</rz>
				<state>0</state>
				<occlusion>-1</occlusion>
				<occlusion_kf>-1</occlusion_kf>
				<truncation>-1</truncation>
				<amt_occlusion>0.0</amt_occlusion>
				<amt_occlusion_kf>-1</amt_occlusion_kf>
				<amt_border_l>0.0</amt_border_l>
				<amt_border_r>0.0</amt_border_r>
				<amt_border_kf>-1</amt_border_kf>
			</item>
			<!-- frame 144 -->
			<item>
				<tx>8.585077</tx>
				<ty>-0.116827</ty>
				<tz>-0.912205</tz>
				<rx>0.000000</rx>
				<ry>0.000000</ry>
				<rz>0.029346</rz>
				<state>0</state>
				<occlusion>-1</occlusion>
				<occlusion_kf>-1</occlusion_kf>
				<truncation>-1</truncation>
				<amt_occlusion>0.0</amt_occlusion>
				<amt_occlusion_kf>-1</amt_occlusion_kf>
				<amt_border_l>0.0</amt_border_l>
				<amt_border_r>0.0</amt_border_r>
				<amt_border_kf>-1</amt_border_kf>
			</item>
			<!-- frame 145 -->
			<item>
				<tx>8.597541</tx>
				<ty>-0.117740</ty>
				<tz>-0.913357</tz>
				<rx>0.000000</rx>
				<ry>0.000000</ry>
				<rz>0.029346</rz>
				<state>0</state>
				<occlusion>-1</occlusion>
				<occlusion_kf>-1</occlusion_kf>
				<truncation>-1</truncation>
				<amt_occlusion>0.0</amt_occlusion>
				<amt_occlusion_kf>-1</amt_occlusion_kf>
				<amt_border_l>0.0</amt_border_l>
				<amt_border_r>0.0</amt_border_r>
				<amt_border_kf>-1</amt_border_kf>
			</item>
			<!-- frame 146 -->
			<item>
				<tx>8.611106</tx>
				<ty>-0.118729</ty>
				<tz>-0.914513</tz>
				<rx>0.000000</rx>
				<ry>0.000000</ry>
				<rz>0.029346</rz>
				<state>0</state>
				<occlusion>-1</occlusion>
				<occlusion_kf>-1</occlusion_kf>
				<truncation>-1</truncation>
				<amt_occlusion>0.0</amt_occlusion>
				<amt_occlusion_kf>-1</amt_occlusion_kf>
				<amt_border_l>0.0</amt_border_l>
				<amt_border_r>0.0</amt_border_r>
				<amt_border_kf>-1</amt_border_kf>
			</item>
			<!-- frame 147 -->
			<item>
				<tx>8.587916</tx>
				<ty>-0.116147</ty>
				<tz>-0.922731</tz>
				<rx>0.000000</rx>
				<ry>0.000000</ry>
				<rz>0.035445</rz>
				<state>0</state>
				<occlusion>-1</occlusion>
				<occlusion_kf>-1</occlusion_kf>
				<truncation>-1</truncation>
				<amt_occlusion>0.0</amt_occlusion>
				<amt_occlusion_kf>-1</amt_occlusion_kf>
				<amt_border_l>0.0</amt_border_l>
				<amt_border_r>0.0</amt_border_r>
				<amt_border_kf>-1</amt_border_kf>
			</item>
			<!-- frame 148 -->
			<item>
				<tx>8.598336</tx>
				<ty>-0.117082</ty>
				<tz>-0.924302</tz>
				<rx>0.000000</rx>
				<ry>0.000000</ry>
				<rz>0.035445</rz>
				<state>0</state>
				<occlusion>-1</occlusion>
				<occlusion_kf>-1</occlusion_kf>
				<truncation>-1</truncation>
				<amt_occlusion>0.0</amt_occlusion>
				<amt_occlusion_kf>-1</amt_occlusion_kf>
				<amt_border_l>0.0</amt_border_l>
				<amt_border_r>0.0</amt_border_r>
				<amt_border_kf>-1</amt_border_kf>
			</item>
			<!-- frame 149 -->
			<item>
				<tx>8.567193</tx>
				<ty>-0.121717</ty>
				<tz>-0.916389</tz>
				<rx>0.000000</rx>
				<ry>0.000000</ry>
				<rz>0.037997</rz>
				<state>0</state>
				<occlusion>-1</occlusion>
				<occlusion_kf>-1</occlusion_kf>
				<truncation>-1</truncation>
				<amt_occlusion>0.0</amt_occlusion>
				<amt_occlusion_kf>-1</amt_occlusion_kf>
				<amt_border_l>0.0</amt_border_l>
				<amt_border_r>0.0</amt_border_r>
				<amt_border_kf>-1</amt_border_kf>
			</item>
			<!-- frame 150 -->
			<item>
				<tx>8.572747</tx>
				<ty>-0.123020</ty>
				<tz>-0.917405</tz>
				<rx>0.000000</rx>
				<ry>0.000000</ry>
				<rz>0.037997</rz>
				<state>0</state>
				<occlusion>-1</occlusion>
				<occlusion_kf>-1</occlusion_kf>
				<truncation>-1</truncation>
				<amt_occlusion>0.0</amt_occlusion>
				<amt_occlusion_kf>-1</amt_occlusion_kf>
				<amt_border_l>0.0</amt_border_l>
				<amt_border_r>0.0</amt_border_r>
				<amt_border_kf>-1</amt_border_kf>
			</item>
			<!-- frame 151 -->
			<item>
				<tx>8.552732</tx>
				<ty>-0.140590</ty>
				<tz>-0.912275</tz>
				<rx>0.000000</rx>
				<ry>0.000000</ry>
				<rz>0.023113</rz>
				<state>0</state>
				<occlusion>-1</occlusion>
				<occlusion_kf>-1</occlusion_kf>
				<truncation>-1</truncation>
				<amt_occlusion>0.0</amt_occlusion>
				<amt_occlusion_kf>-1</amt_occlusion_kf>
				<amt_border_l>0.0</amt_border_l>
				<amt_border_r>0.0</amt_border_r>
				<amt_border_kf>-1</amt_border_kf>
			</item>
			<!-- frame 152 -->
			<item>
				<tx>8.554999</tx>
				<ty>-0.143093</ty>
				<tz>-0.912901</tz>
				<rx>0.000000</rx>
				<ry>0.000000</ry>
				<rz>0.023113</rz>
				<state>0</state>
				<occlusion>-1</occlusion>
				<occlusion_kf>-1</occlusion_kf>
				<truncation>-1</truncation>
				<amt_occlusion>0.0</amt_occlusion>
				<amt_occlusion_kf>-1</amt_occlusion_kf>
				<amt_border_l>0.0</amt_border_l>
				<amt_border_r>0.0</amt_border_r>
				<amt_border_kf>-1</amt_border_kf>
			</item>
			<!-- frame 153 -->
			<item>
				<tx>8.557459</tx>
				<ty>-0.145692</ty>
				<tz>-0.913519</tz>
				<rx>0.000000</rx>
				<ry>0.000000</ry>
				<rz>0.023113</rz>
				<state>0</state>
				<occlusion>-1</occlusion>
				<occlusion_kf>-1</occlusion_kf>
				<truncation>-1</truncation>
				<amt_occlusion>0.0</amt_occlusion>
				<amt_occlusion_kf>-1</amt_occlusion_kf>
				<amt_border_l>0.0</amt_border_l>
				<amt_border_r>0.0</amt_border_r>
				<amt_border_kf>-1</amt_border_kf>
			</item>
			<!-- frame 154 -->
			<item>
				<tx>8.556040</tx>
				<ty>-0.135112</ty>
				<tz>-0.917893</tz>
				<rx>0.000000</rx>
				<ry>0.000000</ry>
				<rz>0.039367</rz>
				<state>0</state>
				<occlusion>-1</occlusion>
				<occlusion_kf>-1</occlusion_kf>
				<truncation>-1</truncation>
				<amt_occlusion>0.0</amt_occlusion>
				<amt_occlusion_kf>-1</amt_occlusion_kf>
				<amt_border_l>0.0</amt_border_l>
				<amt_border_r>0.0</amt_border_r>
				<amt_border_kf>-1</amt_border_kf>
			</item>
			<!-- frame 155 -->
			<item>
				<tx>8.558307</tx>
				<ty>-0.137144</ty>
				<tz>-0.918718</tz>
				<rx>0.000000</rx>
				<ry>0.000000</ry>
				<rz>0.039367</rz>
				<state>0</state>
				<occlusion>-1</occlusion>
				<occlusion_kf>-1</occlusion_kf>
				<truncation>-1</truncation>
				<amt_occlusion>0.0</amt_occlusion>
				<amt_occlusion_kf>-1</amt_occlusion_kf>
				<amt_border_l>0.0</amt_border_l>
				<amt_border_r>0.0</amt_border_r>
				<amt_border_kf>-1</amt_border_kf>
			</item>
			<!-- frame 156 -->
			<item>
				<tx>8.561564</tx>
				<ty>-0.134761</ty>
				<tz>-0.918327</tz>
				<rx>0.000000</rx>
				<ry>0.000000</ry>
				<rz>0.029037</rz>
				<state>0</state>
				<occlusion>-1</occlusion>
				<occlusion_kf>-1</occlusion_kf>
				<truncation>-1</truncation>
				<amt_occlusion>0.0</amt_occlusion>
				<amt_occlusion_kf>-1</amt_occlusion_kf>
				<amt_border_l>0.0</amt_border_l>
				<amt_border_r>0.0</amt_border_r>
				<amt_border_kf>-1</amt_border_kf>
			</item>
			<!-- frame 157 -->
			<item>
				<tx>8.564278</tx>
				<ty>-0.136674</ty>
				<tz>-0.919070</tz>
				<rx>0.000000</rx>
				<ry>0.000000</ry>
				<rz>0.029037</rz>
				<state>0</state>
				<occlusion>-1</occlusion>
				<occlusion_kf>-1</occlusion_kf>
				<truncation>-1</truncation>
				<amt_occlusion>0.0</amt_occlusion>
				<amt_occlusion_kf>-1</amt_occlusion_kf>
				<amt_border_l>0.0</amt_border_l>
				<amt_border_r>0.0</amt_border_r>
				<amt_border_kf>-1</amt_border_kf>
			</item>
			<!-- frame 158 -->
			<item>
				<tx>8.567169</tx>
				<ty>-0.138669</ty>
				<tz>-0.919811</tz>
				<rx>0.000000</rx>
				<ry>0.000000</ry>
				<rz>0.029037</rz>
				<state>0</state>
				<occlusion>-1</occlusion>
				<occlusion_kf>-1</occlusion_kf>
				<truncation>-1</truncation>
				<amt_occlusion>0.0</amt_occlusion>
				<amt_occlusion_kf>-1</amt_occlusion_kf>
				<amt_border_l>0.0</amt_border_l>
				<amt_border_r>0.0</amt_border_r>
				<amt_border_kf>-1</amt_border_kf>
			</item>
			<!-- frame 159 -->
			<item>
				<tx>8.566370</tx>
				<ty>-0.131091</ty>
				<tz>-0.915196</tz>
				<rx>0.000000</rx>
				<ry>0.000000</ry>
				<rz>0.028363</rz>
				<state>0</state>
				<occlusion>-1</occlusion>
				<occlusion_kf>-1</occlusion_kf>
				<truncation>-1</truncation>
				<amt_occlusion>0.0</amt_occlusion>
				<amt_occlusion_kf>-1</amt_occlusion_kf>
				<amt_border_l>0.0</amt_border_l>
				<amt_border_r>0.0</amt_border_r>
				<amt_border_kf>-1</amt_border_kf>
			</item>
			<!-- frame 160 -->
			<item>
				<tx>8.569063</tx>
				<ty>-0.132695</ty>
				<tz>-0.915626</tz>
				<rx>0.000000</rx>
				<ry>0.000000</ry>
				<rz>0.028363</rz>
				<state>0</state>
				<occlusion>-1</occlusion>
				<occlusion_kf>-1</occlusion_kf>
				<truncation>-1</truncation>
				<amt_occlusion>0.0</amt_occlusion>
				<amt_occlusion_kf>-1</amt_occlusion_kf>
				<amt_border_l>0.0</amt_border_l>
				<amt_border_r>0.0</amt_border_r>
				<amt_border_kf>-1</amt_border_kf>
			</item>
			<!-- frame 161 -->
			<item>
				<tx>8.571504</tx>
				<ty>-0.133699</ty>
				<tz>-0.913498</tz>
				<rx>0.000000</rx>
				<ry>0.000000</ry>
				<rz>0.032151</rz>
				<state>0</state>
				<occlusion>-1</occlusion>
				<occlusion_kf>-1</occlusion_kf>
				<truncation>-1</truncation>
				<amt_occlusion>0.0</amt_occlusion>
				<amt_occlusion_kf>-1</amt_occlusion_kf>
				<amt_border_l>0.0</amt_border_l>
				<amt_border_r>0.0</amt_border_r>
				<amt_border_kf>-1</amt_border_kf>
			</item>
			<!-- frame 162 -->
			<item>
				<tx>8.574405</tx>
				<ty>-0.135385</ty>
				<tz>-0.913748</tz>
				<rx>0.000000</rx>
				<ry>0.000000</ry>
				<rz>0.032151</rz>
				<state>0</state>
				<occlusion>-1</occlusion>
				<occlusion_kf>-1</occlusion_kf>
				<truncation>-1</truncation>
				<amt_occlusion>0.0</amt_occlusion>
				<amt_occlusion_kf>-1</amt_occlusion_kf>
				<amt_border_l>0.0</amt_border_l>
				<amt_border_r>0.0</amt_border_r>
				<amt_border_kf>-1</amt_border_kf>
			</item>
			<!-- frame 163 -->
			<item>
				<tx>8.570600</tx>
				<ty>-0.106873</ty>
				<tz>-0.916081</tz>
				<rx>0.000000</rx>
				<ry>0.000000</ry>
				<rz>0.046295</rz>
				<state>0</state>
				<occlusion>-1</occlusion>
				<occlusion_kf>-1</occlusion_kf>
				<truncation>-1</truncation>
				<amt_occlusion>0.0</amt_occlusion>
				<amt_occlusion_kf>-1</amt_occlusion_kf>
				<amt_border_l>0.0</amt_border_l>
				<amt_border_r>0.0</amt_border_r>
				<amt_border_kf>-1</amt_border_kf>
			</item>
			<!-- frame 164 -->
			<item>
				<tx>8.572682</tx>
				<ty>-0.106741</ty>
				<tz>-0.916440</tz>
				<rx>0.000000</rx>
				<ry>0.000000</ry>
				<rz>0.046295</rz>
				<state>0</state>
				<occlusion>-1</occlusion>
				<occlusion_kf>-1</occlusion_kf>
				<truncation>-1</truncation>
				<amt_occlusion>0.0</amt_occlusion>
				<amt_occlusion_kf>-1</amt_occlusion_kf>
				<amt_border_l>0.0</amt_border_l>
				<amt_border_r>0.0</amt_border_r>
				<amt_border_kf>-1</amt_border_kf>
			</item>
			<!-- frame 165 -->
			<item>
				<tx>8.574825</tx>
				<ty>-0.106632</ty>
				<tz>-0.916787</tz>
				<rx>0.000000</rx>
				<ry>0.000000</ry>
				<rz>0.046295</rz>
				<state>0</state>
				<occlusion>-1</occlusion>
				<occlusion_kf>-1</occlusion_kf>
				<truncation>-1</truncation>
				<amt_occlusion>0.0</amt_occlusion>
				<amt_occlusion_kf>-1</amt_occlusion_kf>
				<amt_border_l>0.0</amt_border_l>
				<amt_border_r>0.0</amt_border_r>
				<amt_border_kf>-1</amt_border_kf>
			</item>
		</poses>
		<finished>1</finished>
	</item>
</tracklets>
</boost_serialization> 
